[
  {
    "Name": "[BF] BlackShark",
    "src ID": null,
    "cs ID": null,
    "discord ID": null,
    "botto ID": "-N8PFNx8c4KKGsUd6Li2",
    "Control": null,
    "F.Track": null,
    "F.Pod": null,
    "Country": null,
    "Region": null,
    "Profile Note": null
  },
  {
    "Name": "[N64E] Glozboy",
    "src ID": null,
    "cs ID": null,
    "discord ID": null,
    "botto ID": "-N8PFO1HB6vBvjNE5o9w",
    "Control": null,
    "F.Track": null,
    "F.Pod": null,
    "Country": null,
    "Region": null,
    "Profile Note": null
  },
  {
    "Name": "[N64E] LordSuprachris",
    "src ID": null,
    "cs ID": null,
    "discord ID": null,
    "botto ID": "-N8PFNyI1UDhBzbzhmsW",
    "Control": null,
    "F.Track": null,
    "F.Pod": null,
    "Country": null,
    "Region": null,
    "Profile Note": null
  },
  {
    "Name": "[??] Sol-Solo",
    "src ID": null,
    "cs ID": null,
    "discord ID": null,
    "botto ID": "-N8PFNxy-LrDwMuKRfLR",
    "Control": null,
    "F.Track": null,
    "F.Pod": null,
    "Country": null,
    "Region": null,
    "Profile Note": null
  },
  {
    "Name": "10003120290",
    "src ID": null,
    "cs ID": null,
    "discord ID": null,
    "botto ID": "-NXpnEsXTIY_h1ddC8v9",
    "Control": null,
    "F.Track": null,
    "F.Pod": null,
    "Country": null,
    "Region": null,
    "Profile Note": null
  },
  {
    "Name": "87Pukeass",
    "src ID": "jn2ow0dj",
    "cs ID": null,
    "discord ID": null,
    "botto ID": "-N943P0CMc81vRaKJd37",
    "Control": null,
    "F.Track": null,
    "F.Pod": null,
    "Country": null,
    "Region": null,
    "Profile Note": null
  },
  {
    "Name": "955561976",
    "src ID": null,
    "cs ID": "24805",
    "discord ID": null,
    "botto ID": "-N8PFNs1tC3vz8JPuwHs",
    "Control": null,
    "F.Track": null,
    "F.Pod": null,
    "Country": "UK",
    "Region": null,
    "Profile Note": null
  },
  {
    "Name": "A_Huge_Nerd",
    "src ID": "jprklok8",
    "cs ID": null,
    "discord ID": null,
    "botto ID": "-N8SO0Ms7DcScrOMOUwD",
    "Control": null,
    "F.Track": null,
    "F.Pod": null,
    "Country": "US",
    "Region": null,
    "Profile Note": null
  },
  {
    "Name": "Accutron",
    "src ID": null,
    "cs ID": "205",
    "discord ID": null,
    "botto ID": "-N8PFNlnBAmq1WTuNFXf",
    "Control": null,
    "F.Track": null,
    "F.Pod": null,
    "Country": "US",
    "Region": null,
    "Profile Note": null
  },
  {
    "Name": "acE",
    "src ID": "y8d2n2mj",
    "cs ID": "32210",
    "discord ID": "468827547228962800, 468827547228962816",
    "botto ID": "-N8SNulaiT4iyp9aw93V",
    "Control": "Keyboard",
    "F.Track": "Dug Derby",
    "F.Pod": null,
    "Country": "DE",
    "Region": null,
    "Profile Note": null
  },
  {
    "Name": "almasaydynov",
    "src ID": "18q5n3d8",
    "cs ID": null,
    "discord ID": null,
    "botto ID": "-N8PFNISz7_sajz7ncgg",
    "Control": null,
    "F.Track": null,
    "F.Pod": null,
    "Country": "RU",
    "Region": null,
    "Profile Note": null
  },
  {
    "Name": "AlwaysMarioKartTour",
    "src ID": null,
    "cs ID": null,
    "discord ID": null,
    "botto ID": null,
    "Control": null,
    "F.Track": null,
    "F.Pod": null,
    "Country": null,
    "Region": null,
    "Profile Note": null
  },
  {
    "Name": "andypanther",
    "src ID": "dx3vw68l",
    "cs ID": null,
    "discord ID": null,
    "botto ID": "-N8PFNB6uJbkfGJeWGxN",
    "Control": null,
    "F.Track": null,
    "F.Pod": null,
    "Country": "CH",
    "Region": null,
    "Profile Note": null
  },
  {
    "Name": "Angelus",
    "src ID": "8gr5od1x",
    "cs ID": null,
    "discord ID": null,
    "botto ID": "-N8PFNgx1ZEVnQ46zkrV",
    "Control": null,
    "F.Track": null,
    "F.Pod": null,
    "Country": "US",
    "Region": null,
    "Profile Note": null
  },
  {
    "Name": "Anthony99",
    "src ID": "68we7v48",
    "cs ID": null,
    "discord ID": null,
    "botto ID": "-NFhwAM54IKbSOIzwWXM",
    "Control": null,
    "F.Track": null,
    "F.Pod": null,
    "Country": "AU",
    "Region": null,
    "Profile Note": null
  },
  {
    "Name": "Astrollphysics",
    "src ID": "98rr2og8",
    "cs ID": null,
    "discord ID": null,
    "botto ID": "-N8PFNdddbes9QB-iE7C",
    "Control": null,
    "F.Track": null,
    "F.Pod": null,
    "Country": "AU",
    "Region": null,
    "Profile Note": null
  },
  {
    "Name": "AusFriedChicken",
    "src ID": "xko1qgm8",
    "cs ID": null,
    "discord ID": null,
    "botto ID": "-N8PFNd4Cvr7NAoh-iHJ",
    "Control": null,
    "F.Track": null,
    "F.Pod": null,
    "Country": "AU",
    "Region": null,
    "Profile Note": null
  },
  {
    "Name": "baddam95",
    "src ID": null,
    "cs ID": "19806",
    "discord ID": null,
    "botto ID": "-N8PFNENSofvEwjlXKXx",
    "Control": null,
    "F.Track": null,
    "F.Pod": null,
    "Country": "UK",
    "Region": null,
    "Profile Note": null
  },
  {
    "Name": "BAEZIN",
    "src ID": null,
    "cs ID": null,
    "discord ID": null,
    "botto ID": "-NFhwALzxvmSGOXrVrdh",
    "Control": null,
    "F.Track": null,
    "F.Pod": null,
    "Country": null,
    "Region": null,
    "Profile Note": null
  },
  {
    "Name": "baguito",
    "src ID": null,
    "cs ID": null,
    "discord ID": "217020278620946433",
    "botto ID": "-NVN24_9KlA0MP7PhUxf",
    "Control": null,
    "F.Track": null,
    "F.Pod": null,
    "Country": null,
    "Region": null,
    "Profile Note": null
  },
  {
    "Name": "Balmas",
    "src ID": null,
    "cs ID": null,
    "discord ID": "201585954731851776",
    "botto ID": "-N8PFO7QoZGJ1-AYbXn6",
    "Control": null,
    "F.Track": null,
    "F.Pod": null,
    "Country": "US",
    "Region": null,
    "Profile Note": null
  },
  {
    "Name": "bananaboatkid",
    "src ID": "7j47wp5j",
    "cs ID": "33914",
    "discord ID": null,
    "botto ID": "-N8PFNVMtNZuy77joO0c",
    "Control": null,
    "F.Track": null,
    "F.Pod": null,
    "Country": "US",
    "Region": null,
    "Profile Note": null
  },
  {
    "Name": "barinelg",
    "src ID": "qjozkl86",
    "cs ID": null,
    "discord ID": null,
    "botto ID": "-N8PFNQaoeM6L6ByIKJN",
    "Control": null,
    "F.Track": null,
    "F.Pod": null,
    "Country": "US",
    "Region": null,
    "Profile Note": null
  },
  {
    "Name": "BaronVonBryan",
    "src ID": null,
    "cs ID": null,
    "discord ID": null,
    "botto ID": "-N8PFO4L5P0oobgLB3vC",
    "Control": null,
    "F.Track": null,
    "F.Pod": null,
    "Country": "US",
    "Region": null,
    "Profile Note": null
  },
  {
    "Name": "basilbowman",
    "src ID": "jp622248",
    "cs ID": null,
    "discord ID": null,
    "botto ID": "-NUyi4GBJVLvZDxvW7zR",
    "Control": null,
    "F.Track": null,
    "F.Pod": null,
    "Country": null,
    "Region": null,
    "Profile Note": null
  },
  {
    "Name": "Bastiproton",
    "src ID": "jmzygg4x",
    "cs ID": null,
    "discord ID": null,
    "botto ID": "-NGs4P-BLmuzkjR_yRHF",
    "Control": null,
    "F.Track": null,
    "F.Pod": null,
    "Country": "NL",
    "Region": null,
    "Profile Note": null
  },
  {
    "Name": "bcond2",
    "src ID": "0jm45pyj",
    "cs ID": null,
    "discord ID": null,
    "botto ID": "-N8PFNfBMcWiAhBAzBL6",
    "Control": null,
    "F.Track": null,
    "F.Pod": null,
    "Country": "AU",
    "Region": null,
    "Profile Note": null
  },
  {
    "Name": "Beleos",
    "src ID": null,
    "cs ID": null,
    "discord ID": null,
    "botto ID": "-N8PFO1vyrwSbgpYlYwd",
    "Control": null,
    "F.Track": null,
    "F.Pod": null,
    "Country": null,
    "Region": null,
    "Profile Note": null
  },
  {
    "Name": "Bimblesnarf",
    "src ID": "kj935pwj",
    "cs ID": null,
    "discord ID": null,
    "botto ID": "-N8PFNNipwieHJGQtORu",
    "Control": null,
    "F.Track": null,
    "F.Pod": null,
    "Country": "NL",
    "Region": null,
    "Profile Note": null
  },
  {
    "Name": "BlackMoonCat",
    "src ID": null,
    "cs ID": "2047",
    "discord ID": null,
    "botto ID": "-N8PFNmG-TVcOWzet-2A",
    "Control": null,
    "F.Track": null,
    "F.Pod": null,
    "Country": "BR",
    "Region": null,
    "Profile Note": null
  },
  {
    "Name": "bluedogrulez",
    "src ID": null,
    "cs ID": "17699",
    "discord ID": null,
    "botto ID": "-N8PFNumfKGXqmMrD2HN",
    "Control": null,
    "F.Track": null,
    "F.Pod": null,
    "Country": "US",
    "Region": null,
    "Profile Note": null
  },
  {
    "Name": "Bob",
    "src ID": null,
    "cs ID": null,
    "discord ID": null,
    "botto ID": "-NNPMkN0dWUp12Hoti24",
    "Control": null,
    "F.Track": null,
    "F.Pod": null,
    "Country": null,
    "Region": null,
    "Profile Note": null
  },
  {
    "Name": "Bottles",
    "src ID": null,
    "cs ID": "13",
    "discord ID": null,
    "botto ID": "-N8PFNqd9uAYzudJry_j",
    "Control": null,
    "F.Track": null,
    "F.Pod": null,
    "Country": "NO",
    "Region": null,
    "Profile Note": null
  },
  {
    "Name": "Botto",
    "src ID": null,
    "cs ID": null,
    "discord ID": null,
    "botto ID": "-NWBvvLQU-5ftsM_mhaG",
    "Control": null,
    "F.Track": null,
    "F.Pod": null,
    "Country": null,
    "Region": null,
    "Profile Note": null
  },
  {
    "Name": "Brian Martin",
    "src ID": null,
    "cs ID": null,
    "discord ID": null,
    "botto ID": "-N8PFO0vtuUJPp0mwMJH",
    "Control": null,
    "F.Track": null,
    "F.Pod": null,
    "Country": null,
    "Region": null,
    "Profile Note": null
  },
  {
    "Name": "Briann",
    "src ID": null,
    "cs ID": "30820",
    "discord ID": null,
    "botto ID": "-N8PFNmR0k08Srgj6gmY",
    "Control": null,
    "F.Track": null,
    "F.Pod": null,
    "Country": "US",
    "Region": null,
    "Profile Note": null
  },
  {
    "Name": "brutal_libre",
    "src ID": null,
    "cs ID": null,
    "discord ID": null,
    "botto ID": "-NNPMkN0dWUp12Hoti26",
    "Control": null,
    "F.Track": null,
    "F.Pod": null,
    "Country": null,
    "Region": null,
    "Profile Note": null
  },
  {
    "Name": "Brylarke",
    "src ID": null,
    "cs ID": "201",
    "discord ID": null,
    "botto ID": "-N8PFNqS2qh1CM36E871",
    "Control": null,
    "F.Track": null,
    "F.Pod": null,
    "Country": "UK",
    "Region": null,
    "Profile Note": null
  },
  {
    "Name": "Bubblejunk",
    "src ID": "5j5qdvwj",
    "cs ID": null,
    "discord ID": null,
    "botto ID": "-N8PFNHdOc9qTaGeypcf",
    "Control": null,
    "F.Track": null,
    "F.Pod": null,
    "Country": "FI",
    "Region": null,
    "Profile Note": null
  },
  {
    "Name": "C7Meteors",
    "src ID": null,
    "cs ID": null,
    "discord ID": null,
    "botto ID": "-N8PFNFuG9gr5XodhZnB",
    "Control": null,
    "F.Track": null,
    "F.Pod": null,
    "Country": null,
    "Region": null,
    "Profile Note": null
  },
  {
    "Name": "CaptainandCoke",
    "src ID": null,
    "cs ID": "17498",
    "discord ID": null,
    "botto ID": "-N8PFNoxlO_JbtPXm3bw",
    "Control": null,
    "F.Track": null,
    "F.Pod": null,
    "Country": "US",
    "Region": null,
    "Profile Note": null
  },
  {
    "Name": "CaptainEmu",
    "src ID": "8rpqqm3j",
    "cs ID": null,
    "discord ID": null,
    "botto ID": "-N8SO0M7VBiy6ozb-eJa",
    "Control": null,
    "F.Track": null,
    "F.Pod": null,
    "Country": "DK",
    "Region": null,
    "Profile Note": null
  },
  {
    "Name": "Castlebravo",
    "src ID": null,
    "cs ID": "5968",
    "discord ID": null,
    "botto ID": "-N8PFNojgP5kvOkRtebF",
    "Control": null,
    "F.Track": null,
    "F.Pod": null,
    "Country": "PL",
    "Region": null,
    "Profile Note": null
  },
  {
    "Name": "CatSharked",
    "src ID": "8dg3p1g8",
    "cs ID": null,
    "discord ID": null,
    "botto ID": "-NJt2sPsyo2gMJsZ-b8v",
    "Control": null,
    "F.Track": null,
    "F.Pod": null,
    "Country": "US",
    "Region": null,
    "Profile Note": null
  },
  {
    "Name": "CDoubleDub26",
    "src ID": "8w1e2pvx",
    "cs ID": null,
    "discord ID": null,
    "botto ID": "-N8SO0LTxiP_BW7U21jD",
    "Control": null,
    "F.Track": null,
    "F.Pod": null,
    "Country": "US",
    "Region": null,
    "Profile Note": null
  },
  {
    "Name": "Cha0smagick",
    "src ID": "j42l33wx",
    "cs ID": null,
    "discord ID": null,
    "botto ID": null,
    "Control": null,
    "F.Track": null,
    "F.Pod": null,
    "Country": "CO",
    "Region": null,
    "Profile Note": null
  },
  {
    "Name": "ChaosDrifting",
    "src ID": "o862vopx",
    "cs ID": null,
    "discord ID": null,
    "botto ID": "-N8PFNfX6igZm7Ij5ODv",
    "Control": null,
    "F.Track": null,
    "F.Pod": null,
    "Country": "US",
    "Region": null,
    "Profile Note": null
  },
  {
    "Name": "chillian",
    "src ID": "8g0d1v1x",
    "cs ID": null,
    "discord ID": null,
    "botto ID": "-NWlmu6nszzfdSF_4NrM",
    "Control": null,
    "F.Track": null,
    "F.Pod": null,
    "Country": "US",
    "Region": null,
    "Profile Note": null
  },
  {
    "Name": "Chris DeMichael",
    "src ID": null,
    "cs ID": null,
    "discord ID": null,
    "botto ID": null,
    "Control": null,
    "F.Track": null,
    "F.Pod": null,
    "Country": null,
    "Region": null,
    "Profile Note": null
  },
  {
    "Name": "Chris Hames",
    "src ID": null,
    "cs ID": null,
    "discord ID": null,
    "botto ID": "-N8PFNxPnvBnj9WZc783",
    "Control": null,
    "F.Track": null,
    "F.Pod": null,
    "Country": null,
    "Region": null,
    "Profile Note": null
  },
  {
    "Name": "Chris Rayola",
    "src ID": null,
    "cs ID": null,
    "discord ID": null,
    "botto ID": "-N8PFNyn2Ei7inEeV79v",
    "Control": null,
    "F.Track": null,
    "F.Pod": null,
    "Country": null,
    "Region": null,
    "Profile Note": null
  },
  {
    "Name": "Chubbzgaming",
    "src ID": "j5weednj",
    "cs ID": null,
    "discord ID": null,
    "botto ID": "-N8PFNZpIeOukAnTJN9U",
    "Control": null,
    "F.Track": null,
    "F.Pod": null,
    "Country": "US",
    "Region": null,
    "Profile Note": null
  },
  {
    "Name": "clowndad",
    "src ID": "xz9ppw48",
    "cs ID": null,
    "discord ID": null,
    "botto ID": "-N8PFNbWRiGsZa_PIWZ3",
    "Control": null,
    "F.Track": null,
    "F.Pod": null,
    "Country": "UK",
    "Region": null,
    "Profile Note": null
  },
  {
    "Name": "Cobalt",
    "src ID": "qj2k43nj",
    "cs ID": "26123",
    "discord ID": null,
    "botto ID": "-N8PFNRla4stEZeziLTB",
    "Control": null,
    "F.Track": null,
    "F.Pod": null,
    "Country": "SG",
    "Region": null,
    "Profile Note": null
  },
  {
    "Name": "Colonialist",
    "src ID": null,
    "cs ID": null,
    "discord ID": "219069072589979649",
    "botto ID": "-NNPMkN0dWUp12Hoti23",
    "Control": null,
    "F.Track": null,
    "F.Pod": null,
    "Country": null,
    "Region": null,
    "Profile Note": null
  },
  {
    "Name": "Colt",
    "src ID": null,
    "cs ID": "7204",
    "discord ID": null,
    "botto ID": "-N8PFNswJw_kcAoPkF-L",
    "Control": null,
    "F.Track": null,
    "F.Pod": null,
    "Country": "US",
    "Region": null,
    "Profile Note": null
  },
  {
    "Name": "Cornilious",
    "src ID": "jo36390j",
    "cs ID": null,
    "discord ID": null,
    "botto ID": "-N8SO0YVPQVmLFiQt2M5",
    "Control": null,
    "F.Track": null,
    "F.Pod": null,
    "Country": "US",
    "Region": null,
    "Profile Note": null
  },
  {
    "Name": "Craig Makepeace",
    "src ID": null,
    "cs ID": null,
    "discord ID": null,
    "botto ID": "-N8PFO0GOgDJfnumlvob",
    "Control": null,
    "F.Track": null,
    "F.Pod": null,
    "Country": null,
    "Region": null,
    "Profile Note": null
  },
  {
    "Name": "Croctus",
    "src ID": null,
    "cs ID": "11338",
    "discord ID": null,
    "botto ID": "-N8PFNiR5yYS85Y58WMW",
    "Control": null,
    "F.Track": null,
    "F.Pod": null,
    "Country": "US",
    "Region": null,
    "Profile Note": null
  },
  {
    "Name": "Curiouscoms",
    "src ID": "816m393x",
    "cs ID": null,
    "discord ID": null,
    "botto ID": "-N8PFNesD1ETlgTCbG4T",
    "Control": null,
    "F.Track": null,
    "F.Pod": null,
    "Country": "US",
    "Region": null,
    "Profile Note": null
  },
  {
    "Name": "Cyber_Levrette",
    "src ID": null,
    "cs ID": null,
    "discord ID": null,
    "botto ID": "-N8PFNznzCAQWrymONeh",
    "Control": null,
    "F.Track": null,
    "F.Pod": null,
    "Country": null,
    "Region": null,
    "Profile Note": null
  },
  {
    "Name": "Cybergeddon",
    "src ID": null,
    "cs ID": null,
    "discord ID": null,
    "botto ID": "-N8PFNV-Ob1PKlN8wu0m",
    "Control": null,
    "F.Track": null,
    "F.Pod": null,
    "Country": null,
    "Region": null,
    "Profile Note": null
  },
  {
    "Name": "daft.moustik",
    "src ID": null,
    "cs ID": "15405",
    "discord ID": null,
    "botto ID": "-N8PFNrdq1Tjpcy4ZFlI",
    "Control": null,
    "F.Track": null,
    "F.Pod": null,
    "Country": "FR",
    "Region": null,
    "Profile Note": null
  },
  {
    "Name": "Daniel Arceo",
    "src ID": null,
    "cs ID": null,
    "discord ID": null,
    "botto ID": "-NFhwALzxvmSGOXrVrdf",
    "Control": null,
    "F.Track": null,
    "F.Pod": null,
    "Country": null,
    "Region": null,
    "Profile Note": null
  },
  {
    "Name": "Daniel Hasting",
    "src ID": null,
    "cs ID": null,
    "discord ID": null,
    "botto ID": "-N8PFNzUp3fwlczxDx1s",
    "Control": null,
    "F.Track": null,
    "F.Pod": null,
    "Country": null,
    "Region": null,
    "Profile Note": null
  },
  {
    "Name": "DankDread",
    "src ID": "48gprl28",
    "cs ID": null,
    "discord ID": null,
    "botto ID": "-N8PFNf226VWNbND2CzR",
    "Control": null,
    "F.Track": null,
    "F.Pod": null,
    "Country": "US",
    "Region": null,
    "Profile Note": null
  },
  {
    "Name": "Darkrai",
    "src ID": null,
    "cs ID": null,
    "discord ID": null,
    "botto ID": "-N8PFO463IovpgBAzrbN",
    "Control": null,
    "F.Track": null,
    "F.Pod": null,
    "Country": null,
    "Region": null,
    "Profile Note": null
  },
  {
    "Name": "DarthMorley",
    "src ID": "jmlq0gz8",
    "cs ID": null,
    "discord ID": null,
    "botto ID": "-N8SO-zKzW7j5tIfT-cw",
    "Control": null,
    "F.Track": null,
    "F.Pod": null,
    "Country": "UK",
    "Region": null,
    "Profile Note": null
  },
  {
    "Name": "DarthXemnas",
    "src ID": null,
    "cs ID": "32331",
    "discord ID": null,
    "botto ID": null,
    "Control": null,
    "F.Track": null,
    "F.Pod": null,
    "Country": "ES",
    "Region": null,
    "Profile Note": null
  },
  {
    "Name": "David Schiering",
    "src ID": null,
    "cs ID": null,
    "discord ID": null,
    "botto ID": "-N8PFO04dCvoZaLzt043",
    "Control": null,
    "F.Track": null,
    "F.Pod": null,
    "Country": null,
    "Region": null,
    "Profile Note": null
  },
  {
    "Name": "David Stubbs",
    "src ID": null,
    "cs ID": "17687",
    "discord ID": null,
    "botto ID": "-N8PFNCzw_gnqRnzRdjl",
    "Control": null,
    "F.Track": null,
    "F.Pod": null,
    "Country": "UK",
    "Region": null,
    "Profile Note": null
  },
  {
    "Name": "dekercastle",
    "src ID": null,
    "cs ID": null,
    "discord ID": null,
    "botto ID": "-N8PFO3rBEzRqY-Iyynk",
    "Control": null,
    "F.Track": null,
    "F.Pod": null,
    "Country": null,
    "Region": null,
    "Profile Note": null
  },
  {
    "Name": "Deku Scrublord",
    "src ID": null,
    "cs ID": null,
    "discord ID": null,
    "botto ID": "-N8PFO26kymwH7eBhVQc",
    "Control": null,
    "F.Track": null,
    "F.Pod": null,
    "Country": null,
    "Region": null,
    "Profile Note": null
  },
  {
    "Name": "Devadip",
    "src ID": "8ewp0d28",
    "cs ID": null,
    "discord ID": null,
    "botto ID": null,
    "Control": null,
    "F.Track": null,
    "F.Pod": null,
    "Country": "CA",
    "Region": null,
    "Profile Note": null
  },
  {
    "Name": "DHR",
    "src ID": null,
    "cs ID": null,
    "discord ID": null,
    "botto ID": "-N8PFO61cfHoPD5KLvGD",
    "Control": null,
    "F.Track": null,
    "F.Pod": null,
    "Country": null,
    "Region": null,
    "Profile Note": null
  },
  {
    "Name": "DIABLO",
    "src ID": null,
    "cs ID": "6549",
    "discord ID": null,
    "botto ID": "-N8PFNifygRb_5k4CeKN",
    "Control": null,
    "F.Track": null,
    "F.Pod": null,
    "Country": "IT",
    "Region": null,
    "Profile Note": null
  },
  {
    "Name": "DigitalUnity",
    "src ID": "98rde56j",
    "cs ID": "32372",
    "discord ID": "410925667060809738",
    "botto ID": "-N8PFNTs-v0DRHQ7vYF5",
    "Control": null,
    "F.Track": null,
    "F.Pod": null,
    "Country": "US",
    "Region": null,
    "Profile Note": null
  },
  {
    "Name": "dkr_paddy",
    "src ID": "v8lg02jm",
    "cs ID": null,
    "discord ID": null,
    "botto ID": "-N8PFNBR6xplf65JuuxK",
    "Control": null,
    "F.Track": null,
    "F.Pod": null,
    "Country": "DE",
    "Region": null,
    "Profile Note": null
  },
  {
    "Name": "dnd",
    "src ID": null,
    "cs ID": "3027",
    "discord ID": null,
    "botto ID": "-N8PFNvebB1hD0AccKWM",
    "Control": null,
    "F.Track": null,
    "F.Pod": null,
    "Country": "UK",
    "Region": null,
    "Profile Note": null
  },
  {
    "Name": "Domirae",
    "src ID": "8145e138",
    "cs ID": "34421",
    "discord ID": "424544208880402443",
    "botto ID": "-N8PFNcQDnLf2Z9nA43n",
    "Control": "Controller",
    "F.Track": "Grabvine Gateway",
    "F.Pod": "Jinn Reeso",
    "Country": "US",
    "Region": null,
    "Profile Note": null
  },
  {
    "Name": "DouchemanMacgee",
    "src ID": null,
    "cs ID": null,
    "discord ID": null,
    "botto ID": null,
    "Control": null,
    "F.Track": null,
    "F.Pod": null,
    "Country": "US",
    "Region": null,
    "Profile Note": null
  },
  {
    "Name": "Dr-Trilogy",
    "src ID": "jo3g770j",
    "cs ID": null,
    "discord ID": null,
    "botto ID": "-N8PFN_8jQKfpXRBO-Xr",
    "Control": null,
    "F.Track": null,
    "F.Pod": null,
    "Country": "US",
    "Region": null,
    "Profile Note": null
  },
  {
    "Name": "Droopy Angora",
    "src ID": "xyo17lwj",
    "cs ID": null,
    "discord ID": "554005837174276097",
    "botto ID": "-NM4pNLbFytD03ex6Goj",
    "Control": "Controller",
    "F.Track": "Dug Derby",
    "F.Pod": "Ben Quadinaros",
    "Country": "FR",
    "Region": null,
    "Profile Note": null
  },
  {
    "Name": "DScoffers",
    "src ID": null,
    "cs ID": "1583",
    "discord ID": null,
    "botto ID": "-N8PFNjnWpL3gImZFOVe",
    "Control": null,
    "F.Track": null,
    "F.Pod": null,
    "Country": "UK",
    "Region": null,
    "Profile Note": null
  },
  {
    "Name": "Dwy Guy",
    "src ID": null,
    "cs ID": "32603",
    "discord ID": null,
    "botto ID": "-N8PFNhdlxE4Dncd0Cge",
    "Control": null,
    "F.Track": null,
    "F.Pod": null,
    "Country": "US",
    "Region": null,
    "Profile Note": null
  },
  {
    "Name": "Eddiechan_",
    "src ID": "j42wlovx",
    "cs ID": null,
    "discord ID": null,
    "botto ID": "-N8PFNfLbEdL6JsW_Z_V",
    "Control": null,
    "F.Track": null,
    "F.Pod": null,
    "Country": "US",
    "Region": null,
    "Profile Note": null
  },
  {
    "Name": "El_Jefe_93",
    "src ID": "8e95dvpj",
    "cs ID": null,
    "discord ID": null,
    "botto ID": "-N8PFNWTdDZuvrVn_bqr",
    "Control": null,
    "F.Track": null,
    "F.Pod": null,
    "Country": "US",
    "Region": null,
    "Profile Note": null
  },
  {
    "Name": "electricyellow",
    "src ID": null,
    "cs ID": null,
    "discord ID": null,
    "botto ID": "-N8PFNKredf4EW9kFocY",
    "Control": null,
    "F.Track": null,
    "F.Pod": null,
    "Country": null,
    "Region": null,
    "Profile Note": null
  },
  {
    "Name": "Eli Young",
    "src ID": null,
    "cs ID": null,
    "discord ID": null,
    "botto ID": "-N8PFO-s_Lyy-Fnhoswp",
    "Control": null,
    "F.Track": null,
    "F.Pod": null,
    "Country": null,
    "Region": null,
    "Profile Note": null
  },
  {
    "Name": "ELI7E_BatMan764",
    "src ID": "8e9o9v2j",
    "cs ID": null,
    "discord ID": null,
    "botto ID": "-N8PFNaO_ZBm1DKwp-Db",
    "Control": null,
    "F.Track": null,
    "F.Pod": null,
    "Country": "AU",
    "Region": null,
    "Profile Note": null
  },
  {
    "Name": "EternalCow",
    "src ID": "jnpmwvd8",
    "cs ID": null,
    "discord ID": null,
    "botto ID": null,
    "Control": null,
    "F.Track": null,
    "F.Pod": null,
    "Country": "US",
    "Region": null,
    "Profile Note": null
  },
  {
    "Name": "Ferggotten",
    "src ID": "xz9zwne8",
    "cs ID": null,
    "discord ID": null,
    "botto ID": "-N8PFNarJ_t7zNlf0GrT",
    "Control": null,
    "F.Track": null,
    "F.Pod": null,
    "Country": "CL",
    "Region": null,
    "Profile Note": null
  },
  {
    "Name": "ffdek",
    "src ID": null,
    "cs ID": null,
    "discord ID": null,
    "botto ID": "-N8PFNwV8QlsHYDNXDpj",
    "Control": null,
    "F.Track": null,
    "F.Pod": null,
    "Country": null,
    "Region": null,
    "Profile Note": null
  },
  {
    "Name": "FFXIHeat",
    "src ID": null,
    "cs ID": "15898",
    "discord ID": null,
    "botto ID": "-N8PFNtO7xTJBwjltVgy",
    "Control": null,
    "F.Track": null,
    "F.Pod": null,
    "Country": "UK",
    "Region": null,
    "Profile Note": null
  },
  {
    "Name": "FierceKai",
    "src ID": null,
    "cs ID": "21443",
    "discord ID": null,
    "botto ID": "-N8PFNiBTyBgbx0UAirx",
    "Control": null,
    "F.Track": null,
    "F.Pod": null,
    "Country": "DE",
    "Region": null,
    "Profile Note": null
  },
  {
    "Name": "Flev48",
    "src ID": "jprqeg58",
    "cs ID": null,
    "discord ID": null,
    "botto ID": "-N8PFNbHYUUjIEUihbpm",
    "Control": null,
    "F.Track": null,
    "F.Pod": null,
    "Country": "UK",
    "Region": null,
    "Profile Note": null
  },
  {
    "Name": "Fly",
    "src ID": null,
    "cs ID": null,
    "discord ID": null,
    "botto ID": null,
    "Control": null,
    "F.Track": null,
    "F.Pod": null,
    "Country": null,
    "Region": null,
    "Profile Note": null
  },
  {
    "Name": "G4merholy",
    "src ID": null,
    "cs ID": "17530",
    "discord ID": null,
    "botto ID": "-N8PFNq0FRTfazXTFfVS",
    "Control": null,
    "F.Track": null,
    "F.Pod": null,
    "Country": "DE",
    "Region": null,
    "Profile Note": null
  },
  {
    "Name": "galeforce",
    "src ID": "qxk6k280",
    "cs ID": "19884",
    "discord ID": null,
    "botto ID": "-N8PFNOI4eEzJOY2B4xE",
    "Control": null,
    "F.Track": null,
    "F.Pod": null,
    "Country": "AU",
    "Region": null,
    "Profile Note": null
  },
  {
    "Name": "Gamedraco",
    "src ID": "7j4zr7dx",
    "cs ID": "15461",
    "discord ID": "536004444341403658",
    "botto ID": "-N8PFNDeDlEAHbsNJANv",
    "Control": "N64 OEM",
    "F.Track": "The Gauntlet",
    "F.Pod": "Bullseye Navoir",
    "Country": "US",
    "Region": null,
    "Profile Note": null
  },
  {
    "Name": "gamewizardx",
    "src ID": null,
    "cs ID": "287",
    "discord ID": null,
    "botto ID": "-N8PFNlRGP0uz7uD7rVD",
    "Control": null,
    "F.Track": null,
    "F.Pod": null,
    "Country": "US",
    "Region": null,
    "Profile Note": null
  },
  {
    "Name": "Gavin Carper",
    "src ID": null,
    "cs ID": null,
    "discord ID": null,
    "botto ID": null,
    "Control": null,
    "F.Track": null,
    "F.Pod": null,
    "Country": null,
    "Region": null,
    "Profile Note": null
  },
  {
    "Name": "GeekyGamer55",
    "src ID": "8q64n1dj",
    "cs ID": null,
    "discord ID": null,
    "botto ID": null,
    "Control": null,
    "F.Track": null,
    "F.Pod": null,
    "Country": "UK",
    "Region": null,
    "Profile Note": null
  },
  {
    "Name": "Genmai",
    "src ID": "j20wq7px",
    "cs ID": null,
    "discord ID": null,
    "botto ID": "-NAFdTbKGE63MCu9ip_B",
    "Control": null,
    "F.Track": null,
    "F.Pod": null,
    "Country": "JP",
    "Region": null,
    "Profile Note": null
  },
  {
    "Name": "Ghost0505a",
    "src ID": "8q34p4wj",
    "cs ID": null,
    "discord ID": "626299264477429778",
    "botto ID": "-N8SO0MosNEKCUJVQE9W",
    "Control": null,
    "F.Track": null,
    "F.Pod": null,
    "Country": "AU",
    "Region": null,
    "Profile Note": null
  },
  {
    "Name": "glennobrien",
    "src ID": "5j5wryzj",
    "cs ID": null,
    "discord ID": null,
    "botto ID": "-N8PFNcDoStRfB0cYoLL",
    "Control": null,
    "F.Track": null,
    "F.Pod": null,
    "Country": "AU",
    "Region": null,
    "Profile Note": null
  },
  {
    "Name": "Goblin Lifestyle",
    "src ID": null,
    "cs ID": null,
    "discord ID": null,
    "botto ID": "-N8PFO2XJLgkc5SEevcs",
    "Control": null,
    "F.Track": null,
    "F.Pod": null,
    "Country": null,
    "Region": null,
    "Profile Note": null
  },
  {
    "Name": "Goensaeg",
    "src ID": null,
    "cs ID": null,
    "discord ID": "321118173523083274",
    "botto ID": null,
    "Control": null,
    "F.Track": null,
    "F.Pod": null,
    "Country": null,
    "Region": null,
    "Profile Note": null
  },
  {
    "Name": "goofbrush",
    "src ID": "qxkppkkj",
    "cs ID": "62268",
    "discord ID": "167721054956027904",
    "botto ID": "-N8PFNh8pxwclWmKyRtc",
    "Control": "Controller",
    "F.Track": "Executioner",
    "F.Pod": "Bozzie Baranta",
    "Country": "UK",
    "Region": null,
    "Profile Note": "? my ?"
  },
  {
    "Name": "Gorton",
    "src ID": null,
    "cs ID": null,
    "discord ID": null,
    "botto ID": "-N8PFO6mESr-KDilYa7m",
    "Control": null,
    "F.Track": null,
    "F.Pod": null,
    "Country": null,
    "Region": null,
    "Profile Note": null
  },
  {
    "Name": "gpape",
    "src ID": "8vogdo5x",
    "cs ID": null,
    "discord ID": null,
    "botto ID": "-N8SNzip6rP05HvzUlKh",
    "Control": null,
    "F.Track": null,
    "F.Pod": null,
    "Country": "CA",
    "Region": null,
    "Profile Note": null
  },
  {
    "Name": "gr95",
    "src ID": "86vpgnqj",
    "cs ID": null,
    "discord ID": null,
    "botto ID": "-N8PFNUSGstNsnSb1vp0",
    "Control": null,
    "F.Track": null,
    "F.Pod": null,
    "Country": "US",
    "Region": null,
    "Profile Note": null
  },
  {
    "Name": "GrandMasterMario5000",
    "src ID": "j964z57j",
    "cs ID": null,
    "discord ID": null,
    "botto ID": "-N8SO0AhuExPnfI1HHuc",
    "Control": null,
    "F.Track": null,
    "F.Pod": null,
    "Country": "CA",
    "Region": null,
    "Profile Note": null
  },
  {
    "Name": "gruetwo",
    "src ID": "xk4p336j",
    "cs ID": null,
    "discord ID": null,
    "botto ID": "-N8PFNeKbTNkb_Oy34pw",
    "Control": null,
    "F.Track": null,
    "F.Pod": null,
    "Country": "US",
    "Region": null,
    "Profile Note": null
  },
  {
    "Name": "guaxizenho",
    "src ID": "8w0w9wlj",
    "cs ID": null,
    "discord ID": null,
    "botto ID": "-NUYwkzevkaXChYQUrC9",
    "Control": null,
    "F.Track": null,
    "F.Pod": null,
    "Country": "BR",
    "Region": null,
    "Profile Note": null
  },
  {
    "Name": "Guillaume Racine",
    "src ID": null,
    "cs ID": null,
    "discord ID": null,
    "botto ID": "-N8PFNxbrsPVv-B92Hd5",
    "Control": null,
    "F.Track": null,
    "F.Pod": null,
    "Country": null,
    "Region": null,
    "Profile Note": null
  },
  {
    "Name": "Guufi",
    "src ID": "qj271ln8",
    "cs ID": null,
    "discord ID": null,
    "botto ID": "-N8PFNPJ4v4w3O_tDTbE",
    "Control": null,
    "F.Track": null,
    "F.Pod": null,
    "Country": "US",
    "Region": null,
    "Profile Note": null
  },
  {
    "Name": "haavarddahle",
    "src ID": null,
    "cs ID": "22270",
    "discord ID": null,
    "botto ID": "-N8PFNm1TnmsKKZYW7MT",
    "Control": null,
    "F.Track": null,
    "F.Pod": null,
    "Country": "NO",
    "Region": null,
    "Profile Note": null
  },
  {
    "Name": "HaNs0n25",
    "src ID": null,
    "cs ID": "6508",
    "discord ID": null,
    "botto ID": "-N8PFNlcdIFqcrTZtG6m",
    "Control": null,
    "F.Track": null,
    "F.Pod": null,
    "Country": "US",
    "Region": null,
    "Profile Note": null
  },
  {
    "Name": "hellfire",
    "src ID": "8rm6ldqj",
    "cs ID": null,
    "discord ID": "200845447131168769",
    "botto ID": "-N8SNvQ4QVNAs8BNX8Ln",
    "Control": "Keyboard",
    "F.Track": "Fire Mountain Rally",
    "F.Pod": "Boles Rohr",
    "Country": "US",
    "Region": "old src 81kk603j",
    "Profile Note": null
  },
  {
    "Name": "Heraald",
    "src ID": "8v5onk2j",
    "cs ID": null,
    "discord ID": null,
    "botto ID": "-N8PFNg8zOfYEGBT8hRl",
    "Control": null,
    "F.Track": null,
    "F.Pod": null,
    "Country": "US",
    "Region": null,
    "Profile Note": null
  },
  {
    "Name": "HollowGod",
    "src ID": "jn35ov2x",
    "cs ID": null,
    "discord ID": null,
    "botto ID": "-N8PFN_fzu45HbrrhWkk",
    "Control": null,
    "F.Track": null,
    "F.Pod": null,
    "Country": null,
    "Region": null,
    "Profile Note": null
  },
  {
    "Name": "Holyman",
    "src ID": "18v1k9v8",
    "cs ID": null,
    "discord ID": null,
    "botto ID": "-N8PFNRVFDzSobJ5GknB",
    "Control": null,
    "F.Track": null,
    "F.Pod": null,
    "Country": "US",
    "Region": null,
    "Profile Note": null
  },
  {
    "Name": "HomuraAkemi",
    "src ID": "j5wg26qj",
    "cs ID": null,
    "discord ID": "698032696882102282",
    "botto ID": "-N8PFNgROvse4SdQvEY5",
    "Control": "Keyboard",
    "F.Track": "Ando Prime Centrum",
    "F.Pod": null,
    "Country": "JP",
    "Region": null,
    "Profile Note": null
  },
  {
    "Name": "Horstmann",
    "src ID": null,
    "cs ID": "2808",
    "discord ID": null,
    "botto ID": "-N8PFNl4fWgPZF8FKYqF",
    "Control": null,
    "F.Track": null,
    "F.Pod": null,
    "Country": "DE",
    "Region": null,
    "Profile Note": null
  },
  {
    "Name": "huiyeong",
    "src ID": "8vo276nx",
    "cs ID": null,
    "discord ID": null,
    "botto ID": "-N8SO0MfxW98DBBr1dP7",
    "Control": null,
    "F.Track": null,
    "F.Pod": null,
    "Country": "KR",
    "Region": null,
    "Profile Note": null
  },
  {
    "Name": "Hyuudoro",
    "src ID": null,
    "cs ID": "32678",
    "discord ID": "446467835481423883",
    "botto ID": "-N8PFNhUfjbflIe3jSPy",
    "Control": "Hori",
    "F.Track": null,
    "F.Pod": null,
    "Country": "CA",
    "Region": null,
    "Profile Note": null
  },
  {
    "Name": "idel",
    "src ID": null,
    "cs ID": null,
    "discord ID": null,
    "botto ID": "-N8PFO5a4yzEanqns7vy",
    "Control": null,
    "F.Track": null,
    "F.Pod": null,
    "Country": null,
    "Region": null,
    "Profile Note": null
  },
  {
    "Name": "imRaiyu",
    "src ID": "8g0nz37x",
    "cs ID": null,
    "discord ID": null,
    "botto ID": "-NKhUSdtgEt2PHk1166X",
    "Control": null,
    "F.Track": null,
    "F.Pod": null,
    "Country": null,
    "Region": null,
    "Profile Note": null
  },
  {
    "Name": "Infesord",
    "src ID": null,
    "cs ID": null,
    "discord ID": null,
    "botto ID": "-N8PFO77q6tK-EkjeRiU",
    "Control": null,
    "F.Track": null,
    "F.Pod": null,
    "Country": null,
    "Region": null,
    "Profile Note": null
  },
  {
    "Name": "jackgarrett",
    "src ID": null,
    "cs ID": "526",
    "discord ID": null,
    "botto ID": "-N8PFNkarhsudhrIGSCI",
    "Control": null,
    "F.Track": null,
    "F.Pod": null,
    "Country": "AU",
    "Region": null,
    "Profile Note": null
  },
  {
    "Name": "Jackson S",
    "src ID": null,
    "cs ID": null,
    "discord ID": null,
    "botto ID": null,
    "Control": null,
    "F.Track": null,
    "F.Pod": null,
    "Country": null,
    "Region": null,
    "Profile Note": null
  },
  {
    "Name": "Jacob Smith",
    "src ID": null,
    "cs ID": null,
    "discord ID": null,
    "botto ID": "-NFhwAM6aEiLX1a4Nb9d",
    "Control": null,
    "F.Track": null,
    "F.Pod": null,
    "Country": null,
    "Region": null,
    "Profile Note": null
  },
  {
    "Name": "Jesse_Lee",
    "src ID": null,
    "cs ID": null,
    "discord ID": null,
    "botto ID": "-N8PFNJFn2DJ07mFBUrd",
    "Control": null,
    "F.Track": null,
    "F.Pod": null,
    "Country": null,
    "Region": null,
    "Profile Note": null
  },
  {
    "Name": "Jisti",
    "src ID": "0jm4w4j1",
    "cs ID": null,
    "discord ID": null,
    "botto ID": "-N8PFNBh23V2UbQOoB_F",
    "Control": null,
    "F.Track": null,
    "F.Pod": null,
    "Country": "FI",
    "Region": null,
    "Profile Note": null
  },
  {
    "Name": "jogilbee",
    "src ID": "8e66597j",
    "cs ID": null,
    "discord ID": null,
    "botto ID": "-N8SO-LxvubeUbWfQV95",
    "Control": null,
    "F.Track": null,
    "F.Pod": null,
    "Country": "US",
    "Region": null,
    "Profile Note": null
  },
  {
    "Name": "John Hunter",
    "src ID": null,
    "cs ID": null,
    "discord ID": null,
    "botto ID": "-NNPMkN0dWUp12Hoti22",
    "Control": null,
    "F.Track": null,
    "F.Pod": null,
    "Country": null,
    "Region": null,
    "Profile Note": null
  },
  {
    "Name": "Jonas_Jones",
    "src ID": "jop5gw7x",
    "cs ID": null,
    "discord ID": null,
    "botto ID": "-N8SNzUA_stu4JZkcwyw",
    "Control": null,
    "F.Track": null,
    "F.Pod": null,
    "Country": null,
    "Region": null,
    "Profile Note": null
  },
  {
    "Name": "Josh Handeland",
    "src ID": null,
    "cs ID": null,
    "discord ID": null,
    "botto ID": "-N8PFNwC9jPDuio5PuR_",
    "Control": null,
    "F.Track": null,
    "F.Pod": null,
    "Country": null,
    "Region": null,
    "Profile Note": null
  },
  {
    "Name": "Juice",
    "src ID": null,
    "cs ID": "711",
    "discord ID": null,
    "botto ID": "-N8PFNo-Uw4zrU-ciVdk",
    "Control": null,
    "F.Track": null,
    "F.Pod": null,
    "Country": "US",
    "Region": null,
    "Profile Note": null
  },
  {
    "Name": "julienSWR",
    "src ID": null,
    "cs ID": null,
    "discord ID": null,
    "botto ID": "-NFhwAM-ZWJKgLZEYdGs",
    "Control": null,
    "F.Track": null,
    "F.Pod": null,
    "Country": null,
    "Region": null,
    "Profile Note": null
  },
  {
    "Name": "K0R8Z",
    "src ID": "8g50677j",
    "cs ID": null,
    "discord ID": null,
    "botto ID": "-NUJp0jAukdvYKDkupDy",
    "Control": null,
    "F.Track": null,
    "F.Pod": null,
    "Country": "AU",
    "Region": null,
    "Profile Note": null
  },
  {
    "Name": "Kanobe",
    "src ID": "zxzrm0r8",
    "cs ID": null,
    "discord ID": null,
    "botto ID": "-N8PFNRCfEmFp8COLNnA",
    "Control": null,
    "F.Track": null,
    "F.Pod": null,
    "Country": "DE",
    "Region": null,
    "Profile Note": null
  },
  {
    "Name": "karmamachine",
    "src ID": null,
    "cs ID": "2712",
    "discord ID": null,
    "botto ID": "-N8PFNkp6Ten4VGcThuX",
    "Control": null,
    "F.Track": null,
    "F.Pod": null,
    "Country": "CA",
    "Region": null,
    "Profile Note": null
  },
  {
    "Name": "Ker_Pouic-Pouic",
    "src ID": "zx72ooq8",
    "cs ID": null,
    "discord ID": null,
    "botto ID": "-N8PFNYep5UQmOlhLFdw",
    "Control": null,
    "F.Track": null,
    "F.Pod": null,
    "Country": "FR",
    "Region": null,
    "Profile Note": null
  },
  {
    "Name": "killer1300",
    "src ID": null,
    "cs ID": null,
    "discord ID": null,
    "botto ID": "-N8PFO16arvLPqV1nWfH",
    "Control": null,
    "F.Track": null,
    "F.Pod": null,
    "Country": null,
    "Region": null,
    "Profile Note": null
  },
  {
    "Name": "kingbeandip",
    "src ID": "18q1gr7x",
    "cs ID": "33622",
    "discord ID": null,
    "botto ID": "-N8PFNNAEOZclvmE3jYs",
    "Control": null,
    "F.Track": null,
    "F.Pod": null,
    "Country": "US",
    "Region": null,
    "Profile Note": null
  },
  {
    "Name": "Kirby54",
    "src ID": null,
    "cs ID": "3467",
    "discord ID": null,
    "botto ID": "-N8PFNuA5mWLghgNqpwu",
    "Control": null,
    "F.Track": null,
    "F.Pod": null,
    "Country": "FR",
    "Region": null,
    "Profile Note": null
  },
  {
    "Name": "KompleX",
    "src ID": "e8enqgo8",
    "cs ID": null,
    "discord ID": null,
    "botto ID": "-N8PFNKJ5PGXUNfAuqYG",
    "Control": null,
    "F.Track": null,
    "F.Pod": null,
    "Country": "CA",
    "Region": null,
    "Profile Note": null
  },
  {
    "Name": "KoRnDuDe19886",
    "src ID": null,
    "cs ID": null,
    "discord ID": null,
    "botto ID": "-NJ9j52oG_qXy__AjtlI",
    "Control": null,
    "F.Track": null,
    "F.Pod": null,
    "Country": null,
    "Region": null,
    "Profile Note": null
  },
  {
    "Name": "KryptoRacer",
    "src ID": "j2y27mp8",
    "cs ID": null,
    "discord ID": "204668342026371073",
    "botto ID": "-N8PFNWt_cNnlLIe2Ppw",
    "Control": null,
    "F.Track": null,
    "F.Pod": null,
    "Country": "US",
    "Region": null,
    "Profile Note": null
  },
  {
    "Name": "kupo212",
    "src ID": null,
    "cs ID": "2185",
    "discord ID": null,
    "botto ID": "-N8PFNlGVAkahFpHf-ck",
    "Control": null,
    "F.Track": null,
    "F.Pod": null,
    "Country": "US",
    "Region": null,
    "Profile Note": null
  },
  {
    "Name": "Le6lindre",
    "src ID": "o865213x",
    "cs ID": null,
    "discord ID": null,
    "botto ID": "-N8PFNQ--THFlUJEU3UG",
    "Control": null,
    "F.Track": null,
    "F.Pod": null,
    "Country": "FR",
    "Region": null,
    "Profile Note": null
  },
  {
    "Name": "LeafgreenSniper",
    "src ID": null,
    "cs ID": null,
    "discord ID": null,
    "botto ID": "-NURcHSCVsb3e1fQYvj5s",
    "Control": null,
    "F.Track": null,
    "F.Pod": null,
    "Country": "US",
    "Region": null,
    "Profile Note": null
  },
  {
    "Name": "LeonAlmasy",
    "src ID": null,
    "cs ID": null,
    "discord ID": null,
    "botto ID": "-NFhwAM-ZWJKgLZEYdGq",
    "Control": null,
    "F.Track": null,
    "F.Pod": null,
    "Country": null,
    "Region": null,
    "Profile Note": null
  },
  {
    "Name": "Lexingway",
    "src ID": "5j5vomg8",
    "cs ID": null,
    "discord ID": null,
    "botto ID": "-N8PFNXiilCwlsNOrZOw",
    "Control": null,
    "F.Track": null,
    "F.Pod": null,
    "Country": "FR",
    "Region": null,
    "Profile Note": null
  },
  {
    "Name": "LightningPirate",
    "src ID": "j5wdpwgj",
    "cs ID": null,
    "discord ID": "256236315144749059",
    "botto ID": "-N8PFNb3Bmoi7zfk_cP4",
    "Control": null,
    "F.Track": null,
    "F.Pod": null,
    "Country": "US",
    "Region": null,
    "Profile Note": null
  },
  {
    "Name": "lil_sunburn",
    "src ID": "68wny948",
    "cs ID": null,
    "discord ID": null,
    "botto ID": "-N8PFNdtq9f3X7avjwW5",
    "Control": null,
    "F.Track": null,
    "F.Pod": null,
    "Country": "US",
    "Region": null,
    "Profile Note": null
  },
  {
    "Name": "liq",
    "src ID": null,
    "cs ID": "10207",
    "discord ID": null,
    "botto ID": "-N8PFNsgOg9040bYwmup",
    "Control": null,
    "F.Track": null,
    "F.Pod": null,
    "Country": "PL",
    "Region": null,
    "Profile Note": null
  },
  {
    "Name": "Ljosalfr",
    "src ID": "8r3ld5w8",
    "cs ID": null,
    "discord ID": null,
    "botto ID": "-N8SO0hrXi-Pnb27r7P5",
    "Control": null,
    "F.Track": null,
    "F.Pod": null,
    "Country": "AU",
    "Region": null,
    "Profile Note": null
  },
  {
    "Name": "LordRa",
    "src ID": "j9pn16wx",
    "cs ID": null,
    "discord ID": null,
    "botto ID": "-NT2XHXGpjU1ajhfGN2T",
    "Control": null,
    "F.Track": null,
    "F.Pod": null,
    "Country": null,
    "Region": null,
    "Profile Note": null
  },
  {
    "Name": "lozplyr89",
    "src ID": "qjogonx6",
    "cs ID": null,
    "discord ID": null,
    "botto ID": "-N8SO0tBHsp_OWr1oS1o",
    "Control": null,
    "F.Track": null,
    "F.Pod": null,
    "Country": "US",
    "Region": null,
    "Profile Note": null
  },
  {
    "Name": "Luciano Medeiros",
    "src ID": null,
    "cs ID": null,
    "discord ID": null,
    "botto ID": "-NFhwALuF9jvhi4N7Z0l",
    "Control": null,
    "F.Track": null,
    "F.Pod": null,
    "Country": "BR",
    "Region": null,
    "Profile Note": null
  },
  {
    "Name": "Lukaz",
    "src ID": null,
    "cs ID": "5375",
    "discord ID": null,
    "botto ID": "-N8PFNtuI8dKtoxGCaAy",
    "Control": null,
    "F.Track": null,
    "F.Pod": null,
    "Country": "BR",
    "Region": null,
    "Profile Note": null
  },
  {
    "Name": "mageius",
    "src ID": null,
    "cs ID": null,
    "discord ID": null,
    "botto ID": "-N8PFO2JvVeZ7GTlaNsb",
    "Control": null,
    "F.Track": null,
    "F.Pod": null,
    "Country": "US",
    "Region": null,
    "Profile Note": null
  },
  {
    "Name": "magoonator",
    "src ID": null,
    "cs ID": "11258",
    "discord ID": null,
    "botto ID": "-N8PFNmxeIw9GiPFe15B",
    "Control": null,
    "F.Track": null,
    "F.Pod": null,
    "Country": "AU",
    "Region": null,
    "Profile Note": null
  },
  {
    "Name": "magus_plays_games",
    "src ID": "j2yp6368",
    "cs ID": null,
    "discord ID": null,
    "botto ID": "-N8PFNUgOSzBZ6-HMjTt",
    "Control": null,
    "F.Track": null,
    "F.Pod": null,
    "Country": "AU",
    "Region": null,
    "Profile Note": null
  },
  {
    "Name": "MaleficMedic",
    "src ID": "0jmee1zx",
    "cs ID": null,
    "discord ID": null,
    "botto ID": "-N8PFNhK5qKywOBu7WW5",
    "Control": null,
    "F.Track": null,
    "F.Pod": null,
    "Country": "US",
    "Region": null,
    "Profile Note": null
  },
  {
    "Name": "Manu",
    "src ID": null,
    "cs ID": "23813",
    "discord ID": null,
    "botto ID": "-N8PFNpkev-sXONCQ18H",
    "Control": null,
    "F.Track": null,
    "F.Pod": null,
    "Country": "DE",
    "Region": null,
    "Profile Note": null
  },
  {
    "Name": "Marmotato",
    "src ID": "zx7m7o6x",
    "cs ID": null,
    "discord ID": null,
    "botto ID": "-N8PFNFIxA6hW_sLpiyT",
    "Control": null,
    "F.Track": null,
    "F.Pod": null,
    "Country": "CL",
    "Region": null,
    "Profile Note": null
  },
  {
    "Name": "mattius",
    "src ID": null,
    "cs ID": "2986",
    "discord ID": null,
    "botto ID": "-N8PFNmbno-qx3ASys_8",
    "Control": null,
    "F.Track": null,
    "F.Pod": null,
    "Country": "US",
    "Region": null,
    "Profile Note": null
  },
  {
    "Name": "mazexz",
    "src ID": null,
    "cs ID": null,
    "discord ID": null,
    "botto ID": "-N8PFO5DAX1G2Bwcq_OQ",
    "Control": null,
    "F.Track": null,
    "F.Pod": null,
    "Country": null,
    "Region": null,
    "Profile Note": null
  },
  {
    "Name": "Melooow",
    "src ID": "8gevm21j",
    "cs ID": null,
    "discord ID": null,
    "botto ID": "-N8PFNc0ATxu0iO3glTz",
    "Control": null,
    "F.Track": null,
    "F.Pod": null,
    "Country": "BR",
    "Region": null,
    "Profile Note": null
  },
  {
    "Name": "MetaKnight454",
    "src ID": null,
    "cs ID": "15401",
    "discord ID": null,
    "botto ID": "-N8PFNnXiJmQdv6TXe-i",
    "Control": null,
    "F.Track": null,
    "F.Pod": null,
    "Country": "US",
    "Region": null,
    "Profile Note": null
  },
  {
    "Name": "metalgearjsn",
    "src ID": null,
    "cs ID": "672",
    "discord ID": null,
    "botto ID": "-N8PFNmmz3rFiCklmEDN",
    "Control": null,
    "F.Track": null,
    "F.Pod": null,
    "Country": "AU",
    "Region": null,
    "Profile Note": null
  },
  {
    "Name": "metallica",
    "src ID": "v81z2vrj",
    "cs ID": "34113",
    "discord ID": "244958045170434050, 244958045170434048",
    "botto ID": "-N8PFNMreNueP8wCFX07",
    "Control": null,
    "F.Track": null,
    "F.Pod": null,
    "Country": "CL",
    "Region": null,
    "Profile Note": null
  },
  {
    "Name": "Metallica (french)",
    "src ID": null,
    "cs ID": "136",
    "discord ID": null,
    "botto ID": "-N8PFNtaxzGj87FpSwvX",
    "Control": null,
    "F.Track": null,
    "F.Pod": null,
    "Country": "FR",
    "Region": null,
    "Profile Note": null
  },
  {
    "Name": "MetalSmasher86",
    "src ID": null,
    "cs ID": "2188",
    "discord ID": null,
    "botto ID": "-N8PFNvvQUhmCjEeQVgi",
    "Control": null,
    "F.Track": null,
    "F.Pod": null,
    "Country": "US",
    "Region": null,
    "Profile Note": null
  },
  {
    "Name": "methodical",
    "src ID": "j0309l4j",
    "cs ID": "34248",
    "discord ID": null,
    "botto ID": "-N8SNzgoqkZt_pvRMPOz",
    "Control": null,
    "F.Track": null,
    "F.Pod": null,
    "Country": "NL",
    "Region": null,
    "Profile Note": null
  },
  {
    "Name": "Mike Lovato",
    "src ID": null,
    "cs ID": null,
    "discord ID": null,
    "botto ID": "-N8PFO1SxsY99i5Wgrwd",
    "Control": null,
    "F.Track": null,
    "F.Pod": null,
    "Country": null,
    "Region": null,
    "Profile Note": null
  },
  {
    "Name": "Mike Pollack",
    "src ID": null,
    "cs ID": null,
    "discord ID": null,
    "botto ID": "-N8PFNwlucr9ZlAPjan8",
    "Control": null,
    "F.Track": null,
    "F.Pod": null,
    "Country": null,
    "Region": null,
    "Profile Note": null
  },
  {
    "Name": "MikeyBurger",
    "src ID": "qj2e66pj",
    "cs ID": "13830",
    "discord ID": "477087276917194752",
    "botto ID": "-N8PFNDBcZCaoD-3_JWW",
    "Control": null,
    "F.Track": null,
    "F.Pod": null,
    "Country": "UK",
    "Region": null,
    "Profile Note": null
  },
  {
    "Name": "Milkynoodles",
    "src ID": "j0nm5998",
    "cs ID": null,
    "discord ID": null,
    "botto ID": "-N8PFN_QJRC7jTpTHbeX",
    "Control": null,
    "F.Track": null,
    "F.Pod": null,
    "Country": "US",
    "Region": null,
    "Profile Note": null
  },
  {
    "Name": "Miniboss",
    "src ID": null,
    "cs ID": "350",
    "discord ID": null,
    "botto ID": "-N8PFNoC4ellmoo1XcqU",
    "Control": null,
    "F.Track": null,
    "F.Pod": null,
    "Country": "US",
    "Region": null,
    "Profile Note": null
  },
  {
    "Name": "mo_moe",
    "src ID": "68w9q54j",
    "cs ID": null,
    "discord ID": null,
    "botto ID": "-N8PFNIttKOocRgGJaiK",
    "Control": null,
    "F.Track": null,
    "F.Pod": null,
    "Country": "CA",
    "Region": null,
    "Profile Note": null
  },
  {
    "Name": "moon7thsky",
    "src ID": null,
    "cs ID": "7782",
    "discord ID": null,
    "botto ID": "-N8PFNsPFU6DzehIx2Wu",
    "Control": null,
    "F.Track": null,
    "F.Pod": null,
    "Country": null,
    "Region": null,
    "Profile Note": null
  },
  {
    "Name": "MopTheSorcerer",
    "src ID": "xz9nq148",
    "cs ID": null,
    "discord ID": null,
    "botto ID": "-N8PFNW8Rn5-JwvOYl3m",
    "Control": null,
    "F.Track": null,
    "F.Pod": null,
    "Country": "US",
    "Region": null,
    "Profile Note": null
  },
  {
    "Name": "MrN",
    "src ID": null,
    "cs ID": "5391",
    "discord ID": null,
    "botto ID": "-N8PFNqnIX_WzE97czDl",
    "Control": null,
    "F.Track": null,
    "F.Pod": null,
    "Country": "AU",
    "Region": null,
    "Profile Note": null
  },
  {
    "Name": "mrneo240",
    "src ID": "7j4zmqmx",
    "cs ID": null,
    "discord ID": null,
    "botto ID": "-N8PFNM0jQ1IIdFpYflJ",
    "Control": null,
    "F.Track": null,
    "F.Pod": null,
    "Country": "US",
    "Region": null,
    "Profile Note": null
  },
  {
    "Name": "Murryduck",
    "src ID": null,
    "cs ID": "16669",
    "discord ID": null,
    "botto ID": "-N8PFNEDW-ViDo9opIsy",
    "Control": null,
    "F.Track": null,
    "F.Pod": null,
    "Country": "US",
    "Region": null,
    "Profile Note": null
  },
  {
    "Name": "Myles Bukrim",
    "src ID": null,
    "cs ID": null,
    "discord ID": null,
    "botto ID": "-N8PFNDr5ePt6ou39xnn",
    "Control": null,
    "F.Track": null,
    "F.Pod": null,
    "Country": "US",
    "Region": null,
    "Profile Note": null
  },
  {
    "Name": "MystikPahndah",
    "src ID": "x35rgg2j",
    "cs ID": null,
    "discord ID": null,
    "botto ID": "-N8PFNWhJXgQrgWF04i1",
    "Control": null,
    "F.Track": null,
    "F.Pod": null,
    "Country": "AU",
    "Region": null,
    "Profile Note": null
  },
  {
    "Name": "NachoBrado",
    "src ID": "v81ke2rj",
    "cs ID": "25495",
    "discord ID": "115279484567027730, 115279484567027721",
    "botto ID": "-N8PFNLSKnN4ApA2lwuR",
    "Control": "Controller",
    "F.Track": "Bumpy's Breakers",
    "F.Pod": "Gasgano",
    "Country": "US",
    "Region": null,
    "Profile Note": null
  },
  {
    "Name": "nafz",
    "src ID": "jn309y1x",
    "cs ID": null,
    "discord ID": null,
    "botto ID": "-N8PFN_tssBj448KhDOL",
    "Control": null,
    "F.Track": null,
    "F.Pod": null,
    "Country": "AU",
    "Region": null,
    "Profile Note": null
  },
  {
    "Name": "Nateman777",
    "src ID": "8dw3v5mj",
    "cs ID": null,
    "discord ID": "760228708832641024",
    "botto ID": "-NWpgmpu3etpeaVefJdu",
    "Control": null,
    "F.Track": null,
    "F.Pod": null,
    "Country": "US",
    "Region": null,
    "Profile Note": null
  },
  {
    "Name": "NektarN",
    "src ID": "kjpq0lyx",
    "cs ID": null,
    "discord ID": null,
    "botto ID": "-N8PFNJgogf1iIf1a_TS",
    "Control": null,
    "F.Track": null,
    "F.Pod": null,
    "Country": "SE",
    "Region": null,
    "Profile Note": null
  },
  {
    "Name": "Nems",
    "src ID": "8qzyped8",
    "cs ID": null,
    "discord ID": null,
    "botto ID": "-N8PFNZ4JCea-77a7UWN",
    "Control": null,
    "F.Track": null,
    "F.Pod": null,
    "Country": null,
    "Region": null,
    "Profile Note": null
  },
  {
    "Name": "Nido-the-Dino",
    "src ID": "8v5z4gyj",
    "cs ID": null,
    "discord ID": null,
    "botto ID": "-N8PFNbnTwzZp8LgPTTb",
    "Control": null,
    "F.Track": null,
    "F.Pod": null,
    "Country": "NO",
    "Region": null,
    "Profile Note": null
  },
  {
    "Name": "NihilistComedyHour",
    "src ID": "qxk6eok8",
    "cs ID": null,
    "discord ID": null,
    "botto ID": "-N8PFNUAJ5w2f4jg6-ik",
    "Control": null,
    "F.Track": null,
    "F.Pod": null,
    "Country": null,
    "Region": null,
    "Profile Note": null
  },
  {
    "Name": "Nimputs",
    "src ID": "qxko0280",
    "cs ID": "25721",
    "discord ID": null,
    "botto ID": "-N8PFNGTr3CNaGEt9dPE",
    "Control": null,
    "F.Track": null,
    "F.Pod": null,
    "Country": "DE",
    "Region": null,
    "Profile Note": null
  },
  {
    "Name": "nintend0g0d",
    "src ID": null,
    "cs ID": "7730",
    "discord ID": null,
    "botto ID": "-N8PFNpW11_nLspN3koF",
    "Control": null,
    "F.Track": null,
    "F.Pod": null,
    "Country": "US",
    "Region": null,
    "Profile Note": null
  },
  {
    "Name": "Nok",
    "src ID": "x7mqrk6x",
    "cs ID": null,
    "discord ID": "172237358681292801",
    "botto ID": "-N8SNzwS1T2qfXzyHxky",
    "Control": null,
    "F.Track": null,
    "F.Pod": null,
    "Country": "US",
    "Region": null,
    "Profile Note": null
  },
  {
    "Name": "NorCalLime",
    "src ID": "8e6pn17j",
    "cs ID": null,
    "discord ID": null,
    "botto ID": "-N8SO0Ms7DcScrOMOUwE",
    "Control": null,
    "F.Track": null,
    "F.Pod": null,
    "Country": "US",
    "Region": null,
    "Profile Note": null
  },
  {
    "Name": "nstinson",
    "src ID": null,
    "cs ID": "2934",
    "discord ID": null,
    "botto ID": "-N8PFNpLiRofoLzd75t5",
    "Control": null,
    "F.Track": null,
    "F.Pod": null,
    "Country": "US",
    "Region": null,
    "Profile Note": null
  },
  {
    "Name": "Ogris",
    "src ID": "y8dz9zlj",
    "cs ID": null,
    "discord ID": null,
    "botto ID": "-N8PFNPf9Da64vg_yMej",
    "Control": null,
    "F.Track": null,
    "F.Pod": null,
    "Country": "SI",
    "Region": null,
    "Profile Note": null
  },
  {
    "Name": "onedes91",
    "src ID": "j2yw4kn8",
    "cs ID": null,
    "discord ID": null,
    "botto ID": "-N8PFNTPc8NoLDq3_a8P",
    "Control": null,
    "F.Track": null,
    "F.Pod": null,
    "Country": null,
    "Region": null,
    "Profile Note": null
  },
  {
    "Name": "Oplexitie",
    "src ID": null,
    "cs ID": null,
    "discord ID": "287575722086760450",
    "botto ID": "-NURcHSCVsb3e1fQYvjs",
    "Control": null,
    "F.Track": null,
    "F.Pod": null,
    "Country": null,
    "Region": null,
    "Profile Note": null
  },
  {
    "Name": "ottotonsorialist",
    "src ID": "qxk4239j",
    "cs ID": null,
    "discord ID": null,
    "botto ID": "-N8PFNEr4-6eOtlsM-03",
    "Control": null,
    "F.Track": null,
    "F.Pod": null,
    "Country": "US",
    "Region": null,
    "Profile Note": null
  },
  {
    "Name": "OwlfoxXIII",
    "src ID": null,
    "cs ID": null,
    "discord ID": null,
    "botto ID": "-NFhwALwaH6B-yXuz_YN",
    "Control": null,
    "F.Track": null,
    "F.Pod": null,
    "Country": "US",
    "Region": null,
    "Profile Note": null
  },
  {
    "Name": "Paige",
    "src ID": "qxkol780",
    "cs ID": "32730",
    "discord ID": "84078931476512770",
    "botto ID": "-N8PFNLj9zFfWO5bvu4g",
    "Control": "Keyboard",
    "F.Track": null,
    "F.Pod": "Elan Mak",
    "Country": "US",
    "Region": null,
    "Profile Note": null
  },
  {
    "Name": "PAJ",
    "src ID": null,
    "cs ID": null,
    "discord ID": null,
    "botto ID": null,
    "Control": null,
    "F.Track": null,
    "F.Pod": null,
    "Country": null,
    "Region": null,
    "Profile Note": null
  },
  {
    "Name": "Parthros",
    "src ID": "j2wdmz6j",
    "cs ID": null,
    "discord ID": null,
    "botto ID": "-N8PFNgIcR3J-ywrYUW1",
    "Control": null,
    "F.Track": null,
    "F.Pod": null,
    "Country": "US",
    "Region": null,
    "Profile Note": null
  },
  {
    "Name": "passere",
    "src ID": "qjnrvz1x",
    "cs ID": null,
    "discord ID": null,
    "botto ID": "-NDQj16UwY1pqTs67Wii",
    "Control": null,
    "F.Track": null,
    "F.Pod": null,
    "Country": "US",
    "Region": null,
    "Profile Note": null
  },
  {
    "Name": "peebens",
    "src ID": "x3wyzpkj",
    "cs ID": null,
    "discord ID": null,
    "botto ID": "-NVDCh63od3vIgbvU_IG",
    "Control": null,
    "F.Track": null,
    "F.Pod": null,
    "Country": "UK",
    "Region": null,
    "Profile Note": null
  },
  {
    "Name": "Pengy",
    "src ID": "dx3wrkjl",
    "cs ID": null,
    "discord ID": null,
    "botto ID": "-N8PFNX57OOlkLPzxwfK",
    "Control": null,
    "F.Track": null,
    "F.Pod": null,
    "Country": "CH",
    "Region": null,
    "Profile Note": null
  },
  {
    "Name": "perpetucake",
    "src ID": "48ged91j",
    "cs ID": null,
    "discord ID": null,
    "botto ID": "-N8PFNEbrFjeDF3g6kIe",
    "Control": null,
    "F.Track": null,
    "F.Pod": null,
    "Country": "US",
    "Region": null,
    "Profile Note": null
  },
  {
    "Name": "PeterAfro",
    "src ID": "18vk7vjl",
    "cs ID": null,
    "discord ID": null,
    "botto ID": "-N8PFNL6Fz99dB3LcIkW",
    "Control": null,
    "F.Track": null,
    "F.Pod": null,
    "Country": "US",
    "Region": null,
    "Profile Note": null
  },
  {
    "Name": "PiKitsune",
    "src ID": "5j5nonzj",
    "cs ID": null,
    "discord ID": null,
    "botto ID": "-N8PFNJzA329bpmWNvru",
    "Control": null,
    "F.Track": null,
    "F.Pod": null,
    "Country": "US",
    "Region": null,
    "Profile Note": null
  },
  {
    "Name": "Platnuu",
    "src ID": "dx3em52j",
    "cs ID": null,
    "discord ID": null,
    "botto ID": "-NRa1-JqFpaXWwutFZX9",
    "Control": null,
    "F.Track": null,
    "F.Pod": null,
    "Country": "BG",
    "Region": null,
    "Profile Note": null
  },
  {
    "Name": "PlayDeD",
    "src ID": "18v07lnx",
    "cs ID": null,
    "discord ID": null,
    "botto ID": "-N8PFNI2BoyQ0VONG9nN",
    "Control": null,
    "F.Track": null,
    "F.Pod": null,
    "Country": "AU",
    "Region": null,
    "Profile Note": null
  },
  {
    "Name": "Pluto Gam",
    "src ID": null,
    "cs ID": null,
    "discord ID": null,
    "botto ID": null,
    "Control": null,
    "F.Track": null,
    "F.Pod": null,
    "Country": null,
    "Region": null,
    "Profile Note": null
  },
  {
    "Name": "Poschka",
    "src ID": null,
    "cs ID": null,
    "discord ID": null,
    "botto ID": "-NYt-5a3B_mfOws346fR",
    "Control": null,
    "F.Track": null,
    "F.Pod": null,
    "Country": null,
    "Region": null,
    "Profile Note": null
  },
  {
    "Name": "PuffyBall",
    "src ID": null,
    "cs ID": null,
    "discord ID": null,
    "botto ID": "-N8PFNe6XrNaByTC8eAO",
    "Control": null,
    "F.Track": null,
    "F.Pod": null,
    "Country": null,
    "Region": null,
    "Profile Note": null
  },
  {
    "Name": "punchmepat",
    "src ID": "864p100j",
    "cs ID": null,
    "discord ID": null,
    "botto ID": "-NE9ma-eoJGrGorrt2nK",
    "Control": null,
    "F.Track": null,
    "F.Pod": null,
    "Country": null,
    "Region": null,
    "Profile Note": null
  },
  {
    "Name": "PuphyBerry",
    "src ID": "xyrm0gyj",
    "cs ID": null,
    "discord ID": null,
    "botto ID": "-N8SNyqrFivmG7w2Nd8v",
    "Control": null,
    "F.Track": null,
    "F.Pod": null,
    "Country": "US",
    "Region": null,
    "Profile Note": null
  },
  {
    "Name": "Qui-Gon  Gave Up",
    "src ID": null,
    "cs ID": null,
    "discord ID": null,
    "botto ID": "-NURcHSCVsb3e1fQYvj4s",
    "Control": null,
    "F.Track": null,
    "F.Pod": null,
    "Country": "AU",
    "Region": null,
    "Profile Note": null
  },
  {
    "Name": "R2Powered",
    "src ID": "98r31g81",
    "cs ID": "24239",
    "discord ID": null,
    "botto ID": "-N8PFNDNozmAuqcfzn9b",
    "Control": null,
    "F.Track": null,
    "F.Pod": null,
    "Country": "US",
    "Region": null,
    "Profile Note": null
  },
  {
    "Name": "Raken",
    "src ID": null,
    "cs ID": "5403",
    "discord ID": null,
    "botto ID": "-N8PFNit4BEZpbCr5pYC",
    "Control": null,
    "F.Track": null,
    "F.Pod": null,
    "Country": "US",
    "Region": null,
    "Profile Note": null
  },
  {
    "Name": "Ranjit Kohli",
    "src ID": null,
    "cs ID": null,
    "discord ID": null,
    "botto ID": "-N8PFNz9LOdgXIOAtA8m",
    "Control": null,
    "F.Track": null,
    "F.Pod": null,
    "Country": null,
    "Region": null,
    "Profile Note": null
  },
  {
    "Name": "razvan7",
    "src ID": null,
    "cs ID": null,
    "discord ID": null,
    "botto ID": "-NT7USm-ElgTV6k2jLoi",
    "Control": null,
    "F.Track": null,
    "F.Pod": null,
    "Country": null,
    "Region": null,
    "Profile Note": null
  },
  {
    "Name": "Rem",
    "src ID": "dx3qqy6j",
    "cs ID": null,
    "discord ID": null,
    "botto ID": "-N8PFNF2KWp446R9QzG5",
    "Control": null,
    "F.Track": null,
    "F.Pod": null,
    "Country": "US",
    "Region": null,
    "Profile Note": null
  },
  {
    "Name": "Renabastet",
    "src ID": "863d7m38",
    "cs ID": null,
    "discord ID": null,
    "botto ID": "-N8SO-zPmBvMhqGpden_",
    "Control": null,
    "F.Track": null,
    "F.Pod": null,
    "Country": "SE",
    "Region": null,
    "Profile Note": null
  },
  {
    "Name": "Renegawd",
    "src ID": "5j5k7zgj",
    "cs ID": "31922",
    "discord ID": "288258590010245100",
    "botto ID": "-N8PFNKa2FUeY6VhVLeb",
    "Control": null,
    "F.Track": null,
    "F.Pod": null,
    "Country": "DE",
    "Region": null,
    "Profile Note": null
  },
  {
    "Name": "Revelation_x",
    "src ID": "qj21qq68",
    "cs ID": null,
    "discord ID": null,
    "botto ID": "-N8PFNSInuhTzTpt54pQ",
    "Control": null,
    "F.Track": null,
    "F.Pod": null,
    "Country": "US",
    "Region": null,
    "Profile Note": null
  },
  {
    "Name": "RichardDelta93",
    "src ID": null,
    "cs ID": "32243",
    "discord ID": null,
    "botto ID": "-N8PFNhv0gUIs8NZZuD9",
    "Control": null,
    "F.Track": null,
    "F.Pod": null,
    "Country": null,
    "Region": null,
    "Profile Note": null
  },
  {
    "Name": "RNPro1",
    "src ID": null,
    "cs ID": null,
    "discord ID": null,
    "botto ID": null,
    "Control": null,
    "F.Track": null,
    "F.Pod": null,
    "Country": null,
    "Region": null,
    "Profile Note": null
  },
  {
    "Name": "rockdet",
    "src ID": "qjo35o0j",
    "cs ID": null,
    "discord ID": null,
    "botto ID": "-N8PFNCYFTOzkHz3OaAZ",
    "Control": null,
    "F.Track": null,
    "F.Pod": null,
    "Country": "CA",
    "Region": null,
    "Profile Note": null
  },
  {
    "Name": "Romain Lebrun",
    "src ID": null,
    "cs ID": null,
    "discord ID": null,
    "botto ID": "-NFhwAMGf_57aS5uxdcc",
    "Control": null,
    "F.Track": null,
    "F.Pod": null,
    "Country": "FR",
    "Region": null,
    "Profile Note": null
  },
  {
    "Name": "roni",
    "src ID": "o86ndkwx",
    "cs ID": "32789",
    "discord ID": "230042853567496192",
    "botto ID": "-N8PFNQq1wS7SxLSyvrS",
    "Control": null,
    "F.Track": null,
    "F.Pod": null,
    "Country": "US",
    "Region": null,
    "Profile Note": null
  },
  {
    "Name": "rpgmanu",
    "src ID": null,
    "cs ID": "290",
    "discord ID": null,
    "botto ID": "-N8PFNrFaB6vv4sDNDuw",
    "Control": null,
    "F.Track": null,
    "F.Pod": null,
    "Country": "FR",
    "Region": null,
    "Profile Note": null
  },
  {
    "Name": "RSDJ",
    "src ID": null,
    "cs ID": null,
    "discord ID": null,
    "botto ID": null,
    "Control": null,
    "F.Track": null,
    "F.Pod": null,
    "Country": null,
    "Region": null,
    "Profile Note": null
  },
  {
    "Name": "RusAD",
    "src ID": "jpr39p28",
    "cs ID": null,
    "discord ID": null,
    "botto ID": "-N8PFNdNN-OXE_yqe-eP",
    "Control": null,
    "F.Track": null,
    "F.Pod": null,
    "Country": "RU",
    "Region": null,
    "Profile Note": null
  },
  {
    "Name": "scoaps",
    "src ID": null,
    "cs ID": "8278",
    "discord ID": null,
    "botto ID": "-N8PFNv14rC1nil0t1Mq",
    "Control": null,
    "F.Track": null,
    "F.Pod": null,
    "Country": null,
    "Region": null,
    "Profile Note": null
  },
  {
    "Name": "SCREAMNBY",
    "src ID": null,
    "cs ID": "24634",
    "discord ID": null,
    "botto ID": "-N8PFNvMUQazhBKsymR9",
    "Control": null,
    "F.Track": null,
    "F.Pod": null,
    "Country": "US",
    "Region": null,
    "Profile Note": null
  },
  {
    "Name": "sea_leon",
    "src ID": null,
    "cs ID": null,
    "discord ID": null,
    "botto ID": "-NYtNuzOFaH_T7KY_YtG",
    "Control": null,
    "F.Track": null,
    "F.Pod": null,
    "Country": null,
    "Region": null,
    "Profile Note": null
  },
  {
    "Name": "SevenFisher",
    "src ID": null,
    "cs ID": "1021",
    "discord ID": null,
    "botto ID": "-N8PFNr-5WWv5lqXxfsu",
    "Control": null,
    "F.Track": null,
    "F.Pod": null,
    "Country": "UK",
    "Region": null,
    "Profile Note": null
  },
  {
    "Name": "Shadowworld",
    "src ID": "j2wo3llj",
    "cs ID": null,
    "discord ID": null,
    "botto ID": "-N8PFNfmO-orU_GCM24T",
    "Control": null,
    "F.Track": null,
    "F.Pod": null,
    "Country": "US",
    "Region": null,
    "Profile Note": null
  },
  {
    "Name": "Sharky2017",
    "src ID": null,
    "cs ID": "23605",
    "discord ID": null,
    "botto ID": "-N8PFNnmSPIG0B99-u5b",
    "Control": null,
    "F.Track": null,
    "F.Pod": null,
    "Country": "US",
    "Region": null,
    "Profile Note": null
  },
  {
    "Name": "SiniDash",
    "src ID": "j5w1ogwj",
    "cs ID": null,
    "discord ID": null,
    "botto ID": "-N8PFNT9cTVaVNzvVwoM",
    "Control": null,
    "F.Track": null,
    "F.Pod": null,
    "Country": "VE",
    "Region": null,
    "Profile Note": null
  },
  {
    "Name": "Sire",
    "src ID": null,
    "cs ID": null,
    "discord ID": null,
    "botto ID": "-N8PFO2x19BWUdoJ8IgV",
    "Control": null,
    "F.Track": null,
    "F.Pod": null,
    "Country": null,
    "Region": null,
    "Profile Note": null
  },
  {
    "Name": "Skywalker",
    "src ID": null,
    "cs ID": "6959",
    "discord ID": null,
    "botto ID": "-N8PFNoPGGGq6uWJGJP1",
    "Control": null,
    "F.Track": null,
    "F.Pod": null,
    "Country": "RU",
    "Region": null,
    "Profile Note": null
  },
  {
    "Name": "sleepywolff",
    "src ID": null,
    "cs ID": null,
    "discord ID": null,
    "botto ID": "-NFhwALyp5YSyJwiiH-R",
    "Control": null,
    "F.Track": null,
    "F.Pod": null,
    "Country": null,
    "Region": null,
    "Profile Note": null
  },
  {
    "Name": "sluggywuggy",
    "src ID": "qj2y4z78",
    "cs ID": null,
    "discord ID": null,
    "botto ID": "-N8SNuogH2gDh8Q1UOoN",
    "Control": null,
    "F.Track": null,
    "F.Pod": null,
    "Country": "US",
    "Region": null,
    "Profile Note": null
  },
  {
    "Name": "Solune42",
    "src ID": "xkoogo78",
    "cs ID": null,
    "discord ID": null,
    "botto ID": "-N8PFNSaSLMwAYbWXJQ6",
    "Control": null,
    "F.Track": null,
    "F.Pod": null,
    "Country": "US",
    "Region": null,
    "Profile Note": null
  },
  {
    "Name": "spenser9701",
    "src ID": "j426e6dx",
    "cs ID": null,
    "discord ID": null,
    "botto ID": "-N8PFNeef4s6ZmHwegRX",
    "Control": null,
    "F.Track": null,
    "F.Pod": null,
    "Country": "US",
    "Region": null,
    "Profile Note": null
  },
  {
    "Name": "spookisfat",
    "src ID": null,
    "cs ID": "118",
    "discord ID": null,
    "botto ID": "-N8PFNkMTKuDKnB8bLqI",
    "Control": null,
    "F.Track": null,
    "F.Pod": null,
    "Country": "US",
    "Region": null,
    "Profile Note": null
  },
  {
    "Name": "StefanAAB",
    "src ID": null,
    "cs ID": "7637",
    "discord ID": null,
    "botto ID": "-N8PFNp9Y8qw1etfH_xS",
    "Control": null,
    "F.Track": null,
    "F.Pod": null,
    "Country": "NL",
    "Region": null,
    "Profile Note": null
  },
  {
    "Name": "stephengod",
    "src ID": null,
    "cs ID": null,
    "discord ID": null,
    "botto ID": "-N8PFO-ewHaHY-ZBb2Im",
    "Control": null,
    "F.Track": null,
    "F.Pod": null,
    "Country": null,
    "Region": null,
    "Profile Note": null
  },
  {
    "Name": "Steven Hoying",
    "src ID": null,
    "cs ID": null,
    "discord ID": null,
    "botto ID": "-N8PFNxoOYGoiyKIstx2",
    "Control": null,
    "F.Track": null,
    "F.Pod": null,
    "Country": null,
    "Region": null,
    "Profile Note": null
  },
  {
    "Name": "SteveZero",
    "src ID": "o86qprwx",
    "cs ID": null,
    "discord ID": null,
    "botto ID": "-N8PFNggRRCxgJNepZZq",
    "Control": null,
    "F.Track": null,
    "F.Pod": null,
    "Country": "US",
    "Region": null,
    "Profile Note": null
  },
  {
    "Name": "svetlqka",
    "src ID": null,
    "cs ID": null,
    "discord ID": null,
    "botto ID": "-NFcgAzmpMOazN5tbapK",
    "Control": null,
    "F.Track": null,
    "F.Pod": null,
    "Country": null,
    "Region": null,
    "Profile Note": null
  },
  {
    "Name": "SwallowFury",
    "src ID": "j5wr3nwj",
    "cs ID": null,
    "discord ID": null,
    "botto ID": "-N8PFNVhDv7JKzFduAGJ",
    "Control": null,
    "F.Track": null,
    "F.Pod": null,
    "Country": "AU",
    "Region": null,
    "Profile Note": null
  },
  {
    "Name": "sysasysa",
    "src ID": "jpr3rv28",
    "cs ID": null,
    "discord ID": null,
    "botto ID": "-N8PFNTepV73ETZCZxkB",
    "Control": null,
    "F.Track": null,
    "F.Pod": null,
    "Country": "CZ",
    "Region": null,
    "Profile Note": null
  },
  {
    "Name": "tacosrule32",
    "src ID": null,
    "cs ID": null,
    "discord ID": null,
    "botto ID": "-N8PFO0SZnQW73uC56Ad",
    "Control": null,
    "F.Track": null,
    "F.Pod": null,
    "Country": null,
    "Region": null,
    "Profile Note": null
  },
  {
    "Name": "TartarusOfHades",
    "src ID": null,
    "cs ID": null,
    "discord ID": null,
    "botto ID": "-NNPMkN0dWUp12Hoti25",
    "Control": null,
    "F.Track": null,
    "F.Pod": null,
    "Country": null,
    "Region": null,
    "Profile Note": null
  },
  {
    "Name": "Tbence3000",
    "src ID": null,
    "cs ID": null,
    "discord ID": null,
    "botto ID": "-N8PFO6OrOv-KmqwaaGe",
    "Control": null,
    "F.Track": null,
    "F.Pod": null,
    "Country": null,
    "Region": null,
    "Profile Note": null
  },
  {
    "Name": "thats no good",
    "src ID": null,
    "cs ID": null,
    "discord ID": null,
    "botto ID": "-N8PFO3HjHHr3z-yTe4d",
    "Control": null,
    "F.Track": null,
    "F.Pod": null,
    "Country": "UK",
    "Region": null,
    "Profile Note": null
  },
  {
    "Name": "TheCloakedRoach",
    "src ID": "xk42ee2j",
    "cs ID": null,
    "discord ID": null,
    "botto ID": "-N8PFNfyJ_niH2Tvphes",
    "Control": null,
    "F.Track": null,
    "F.Pod": null,
    "Country": "CL",
    "Region": null,
    "Profile Note": null
  },
  {
    "Name": "thedarkangel9090",
    "src ID": null,
    "cs ID": null,
    "discord ID": null,
    "botto ID": "-NJ9j52nP3sPcTkXsc1L",
    "Control": null,
    "F.Track": null,
    "F.Pod": null,
    "Country": null,
    "Region": null,
    "Profile Note": null
  },
  {
    "Name": "theenglishman",
    "src ID": "kjp61y8q",
    "cs ID": null,
    "discord ID": null,
    "botto ID": "-N8PFNCm1DxucNIF4-rs",
    "Control": null,
    "F.Track": null,
    "F.Pod": null,
    "Country": "CA",
    "Region": null,
    "Profile Note": null
  },
  {
    "Name": "TheLouieCopeland",
    "src ID": "8en4lr28",
    "cs ID": null,
    "discord ID": null,
    "botto ID": "-N8SO0tAaIMp8taEDo23",
    "Control": null,
    "F.Track": null,
    "F.Pod": null,
    "Country": "IT",
    "Region": null,
    "Profile Note": null
  },
  {
    "Name": "TheLucas911",
    "src ID": "8rp5redj",
    "cs ID": null,
    "discord ID": null,
    "botto ID": "-N8PFNZRH0eoJvgWvYWz",
    "Control": null,
    "F.Track": null,
    "F.Pod": null,
    "Country": "AU",
    "Region": null,
    "Profile Note": null
  },
  {
    "Name": "ThermalSquare",
    "src ID": "1xy9l9zj",
    "cs ID": null,
    "discord ID": null,
    "botto ID": "-N8PFNYBw4wKHXZxtkis",
    "Control": null,
    "F.Track": null,
    "F.Pod": null,
    "Country": "US",
    "Region": null,
    "Profile Note": null
  },
  {
    "Name": "Thiago Milles Carvalho Dias",
    "src ID": null,
    "cs ID": null,
    "discord ID": null,
    "botto ID": "-N8PFO-4wn6vO5NTw51o",
    "Control": null,
    "F.Track": null,
    "F.Pod": null,
    "Country": null,
    "Region": null,
    "Profile Note": null
  },
  {
    "Name": "ThomasTHF",
    "src ID": null,
    "cs ID": "16953",
    "discord ID": null,
    "botto ID": "-N8PFNj6gRa0jmuCqzWH",
    "Control": null,
    "F.Track": null,
    "F.Pod": null,
    "Country": "DE",
    "Region": null,
    "Profile Note": null
  },
  {
    "Name": "ThrasherDBS",
    "src ID": "8en7gwp8",
    "cs ID": null,
    "discord ID": null,
    "botto ID": "-NUdCBOApD3FkWDXVXuI",
    "Control": null,
    "F.Track": null,
    "F.Pod": null,
    "Country": "US",
    "Region": null,
    "Profile Note": null
  },
  {
    "Name": "Tolarus",
    "src ID": "kjpvp4jq",
    "cs ID": null,
    "discord ID": null,
    "botto ID": "-N8PFNBz_zNHxrraT0CF",
    "Control": null,
    "F.Track": null,
    "F.Pod": null,
    "Country": "US",
    "Region": null,
    "Profile Note": null
  },
  {
    "Name": "Tom Duncan",
    "src ID": null,
    "cs ID": null,
    "discord ID": null,
    "botto ID": null,
    "Control": null,
    "F.Track": null,
    "F.Pod": null,
    "Country": null,
    "Region": null,
    "Profile Note": null
  },
  {
    "Name": "Tonnie Bijlsma",
    "src ID": null,
    "cs ID": null,
    "discord ID": null,
    "botto ID": "-NFyM9vXxVjPKBTY8yN0",
    "Control": null,
    "F.Track": null,
    "F.Pod": null,
    "Country": null,
    "Region": null,
    "Profile Note": null
  },
  {
    "Name": "ToothpasteThy",
    "src ID": "xko302m8",
    "cs ID": "33673",
    "discord ID": null,
    "botto ID": "-N8PFNa6OJ1BpDO3IZws",
    "Control": null,
    "F.Track": null,
    "F.Pod": null,
    "Country": "CA",
    "Region": null,
    "Profile Note": null
  },
  {
    "Name": "tuanif",
    "src ID": null,
    "cs ID": null,
    "discord ID": null,
    "botto ID": null,
    "Control": null,
    "F.Track": null,
    "F.Pod": null,
    "Country": null,
    "Region": null,
    "Profile Note": null
  },
  {
    "Name": "UF7_YO",
    "src ID": "5j5wk26j",
    "cs ID": null,
    "discord ID": null,
    "botto ID": "-N8PFNCIMsK8GIzw98pW",
    "Control": null,
    "F.Track": null,
    "F.Pod": null,
    "Country": "US",
    "Region": null,
    "Profile Note": null
  },
  {
    "Name": "UMEBOSHI",
    "src ID": null,
    "cs ID": null,
    "discord ID": null,
    "botto ID": "-NFhwAMF6FXGVWS8V6zv",
    "Control": null,
    "F.Track": null,
    "F.Pod": null,
    "Country": "JP",
    "Region": null,
    "Profile Note": null
  },
  {
    "Name": "Uncle Vatred",
    "src ID": null,
    "cs ID": null,
    "discord ID": "534239764950548500",
    "botto ID": "-NO6QaxvXLfMiUj8qPfq",
    "Control": null,
    "F.Track": null,
    "F.Pod": null,
    "Country": null,
    "Region": null,
    "Profile Note": null
  },
  {
    "Name": "VolgaAF",
    "src ID": "j4r71pv8",
    "cs ID": null,
    "discord ID": null,
    "botto ID": "-N8PFNXHuO3F_rE51sL6",
    "Control": null,
    "F.Track": null,
    "F.Pod": null,
    "Country": "US",
    "Region": null,
    "Profile Note": null
  },
  {
    "Name": "VulkanMU",
    "src ID": "866py158",
    "cs ID": null,
    "discord ID": null,
    "botto ID": "-N8SO0hyfU3DCghAWEse",
    "Control": null,
    "F.Track": null,
    "F.Pod": null,
    "Country": null,
    "Region": null,
    "Profile Note": null
  },
  {
    "Name": "VVO7",
    "src ID": null,
    "cs ID": "32281",
    "discord ID": null,
    "botto ID": "-N8PFNtAWyNGEz9lwoF3",
    "Control": null,
    "F.Track": null,
    "F.Pod": null,
    "Country": null,
    "Region": null,
    "Profile Note": null
  },
  {
    "Name": "Vykan12",
    "src ID": "5j522qjv",
    "cs ID": null,
    "discord ID": null,
    "botto ID": "-N8PFNMIKDco6N7df6Zp",
    "Control": null,
    "F.Track": null,
    "F.Pod": null,
    "Country": "CA",
    "Region": null,
    "Profile Note": null
  },
  {
    "Name": "Wildchild",
    "src ID": null,
    "cs ID": "1558",
    "discord ID": null,
    "botto ID": "-N8PFNk5gbp85N0DKipG",
    "Control": null,
    "F.Track": null,
    "F.Pod": null,
    "Country": "AT",
    "Region": null,
    "Profile Note": null
  },
  {
    "Name": "Will Rizk",
    "src ID": null,
    "cs ID": null,
    "discord ID": null,
    "botto ID": "-NFhwALyp5YSyJwiiH-T",
    "Control": null,
    "F.Track": null,
    "F.Pod": null,
    "Country": null,
    "Region": null,
    "Profile Note": null
  },
  {
    "Name": "WireyCoyote",
    "src ID": "8w1w9kqx",
    "cs ID": "43323",
    "discord ID": null,
    "botto ID": "-N8SO0MT7MuTr322oTQy",
    "Control": null,
    "F.Track": null,
    "F.Pod": null,
    "Country": "US",
    "Region": null,
    "Profile Note": null
  },
  {
    "Name": "WMJ",
    "src ID": "68wklgl8",
    "cs ID": "8921",
    "discord ID": null,
    "botto ID": "-N8PFNE2I3U0d0ay10TR",
    "Control": null,
    "F.Track": null,
    "F.Pod": null,
    "Country": "NL",
    "Region": null,
    "Profile Note": null
  },
  {
    "Name": "xAdypt",
    "src ID": "jon0v108",
    "cs ID": null,
    "discord ID": "389842489000853514",
    "botto ID": "-NXgYQ_Fn7Y7oLOmf-nW",
    "Control": null,
    "F.Track": null,
    "F.Pod": null,
    "Country": "US",
    "Region": null,
    "Profile Note": null
  },
  {
    "Name": "Xenopholus",
    "src ID": "x76ndw6j",
    "cs ID": null,
    "discord ID": null,
    "botto ID": "-NUyi4EYj-t4vnYtUsDk",
    "Control": null,
    "F.Track": null,
    "F.Pod": null,
    "Country": "US",
    "Region": null,
    "Profile Note": null
  },
  {
    "Name": "Xiavente",
    "src ID": null,
    "cs ID": "33446",
    "discord ID": null,
    "botto ID": "-N8PFNuVNrzaFRkipcuY",
    "Control": null,
    "F.Track": null,
    "F.Pod": null,
    "Country": "HU",
    "Region": null,
    "Profile Note": null
  },
  {
    "Name": "yam",
    "src ID": "816lz13x",
    "cs ID": null,
    "discord ID": null,
    "botto ID": "-N8SNzvYLncqUGdbb3g0",
    "Control": null,
    "F.Track": null,
    "F.Pod": null,
    "Country": "US",
    "Region": null,
    "Profile Note": null
  },
  {
    "Name": "Yaquacus",
    "src ID": null,
    "cs ID": "24599",
    "discord ID": null,
    "botto ID": "-N8PFNjSb7pgj2HedqQ7",
    "Control": null,
    "F.Track": null,
    "F.Pod": null,
    "Country": null,
    "Region": null,
    "Profile Note": null
  },
  {
    "Name": "yellowchu",
    "src ID": null,
    "cs ID": "32614",
    "discord ID": null,
    "botto ID": "-N8PFNrSzs-XtKoAEvCg",
    "Control": null,
    "F.Track": null,
    "F.Pod": null,
    "Country": "US",
    "Region": null,
    "Profile Note": null
  },
  {
    "Name": "yourule970",
    "src ID": "814wgn38",
    "cs ID": null,
    "discord ID": null,
    "botto ID": "-N8PFNS2xtm7qerpGFNn",
    "Control": null,
    "F.Track": null,
    "F.Pod": null,
    "Country": "US",
    "Region": null,
    "Profile Note": null
  },
  {
    "Name": "yuyu",
    "src ID": null,
    "cs ID": null,
    "discord ID": null,
    "botto ID": null,
    "Control": null,
    "F.Track": null,
    "F.Pod": null,
    "Country": "JP",
    "Region": null,
    "Profile Note": null
  },
  {
    "Name": "zakdude100",
    "src ID": "864wy3pj",
    "cs ID": null,
    "discord ID": null,
    "botto ID": "-NJ9j52qdxVkR6nkf9Lj",
    "Control": null,
    "F.Track": null,
    "F.Pod": null,
    "Country": null,
    "Region": null,
    "Profile Note": null
  },
  {
    "Name": "zelascelar",
    "src ID": "jo3q1mlj",
    "cs ID": null,
    "discord ID": "212314806890266620",
    "botto ID": "-N8PFNadRSGpugy8LbmM",
    "Control": null,
    "F.Track": null,
    "F.Pod": null,
    "Country": "SE",
    "Region": null,
    "Profile Note": null
  },
  {
    "Name": "zewing",
    "src ID": "v8l6kr8m",
    "cs ID": null,
    "discord ID": null,
    "botto ID": "-N8PFNQJAQRC66hE_5ZO",
    "Control": null,
    "F.Track": null,
    "F.Pod": null,
    "Country": "US",
    "Region": null,
    "Profile Note": null
  },
  {
    "Name": "Zinfidel",
    "src ID": null,
    "cs ID": null,
    "discord ID": null,
    "botto ID": "-NRa0awhzbWUsBetkqzu",
    "Control": null,
    "F.Track": null,
    "F.Pod": null,
    "Country": null,
    "Region": null,
    "Profile Note": null
  },
  {
    "Name": "Zoki",
    "src ID": null,
    "cs ID": "2551",
    "discord ID": null,
    "botto ID": "-N8PFNqEpkGP_j3oMap1",
    "Control": null,
    "F.Track": null,
    "F.Pod": null,
    "Country": "HR",
    "Region": null,
    "Profile Note": null
  },
  {
    "Name": "Zooty",
    "src ID": "48g70vr8",
    "cs ID": "33935",
    "discord ID": null,
    "botto ID": "-N8SNvrwe1Kd8D-_kE_9",
    "Control": null,
    "F.Track": null,
    "F.Pod": null,
    "Country": "US",
    "Region": null,
    "Profile Note": null
  },
  {
    "Name": "Zorromorph",
    "src ID": null,
    "cs ID": "27187",
    "discord ID": null,
    "botto ID": "-N8PFNnFjig1VFZEm6qX",
    "Control": null,
    "F.Track": null,
    "F.Pod": null,
    "Country": null,
    "Region": null,
    "Profile Note": null
  },
  {
    "Name": "BadlyDrawnDog",
    "src ID": "81mq2g38",
    "cs ID": null,
    "discord ID": "324970648466227210",
    "botto ID": null,
    "Control": null,
    "F.Track": null,
    "F.Pod": null,
    "Country": "HU",
    "Region": null,
    "Profile Note": null
  },
  {
    "Name": "CHELITOXD900",
    "src ID": null,
    "cs ID": null,
    "discord ID": null,
    "botto ID": null,
    "Control": null,
    "F.Track": null,
    "F.Pod": null,
    "Country": "ES",
    "Region": null,
    "Profile Note": null
  },
  {
    "Name": "Sellyme",
    "src ID": null,
    "cs ID": "17598",
    "discord ID": null,
    "botto ID": null,
    "Control": null,
    "F.Track": null,
    "F.Pod": null,
    "Country": "AU",
    "Region": null,
    "Profile Note": null
  },
  {
    "Name": "YellowStarfish92",
    "src ID": null,
    "cs ID": "32887",
    "discord ID": null,
    "botto ID": null,
    "Control": null,
    "F.Track": null,
    "F.Pod": null,
    "Country": "SG",
    "Region": null,
    "Profile Note": null
  },
  {
    "Name": "XxELxJOBIDIAxX",
    "src ID": "8l4lkm2j",
    "cs ID": null,
    "discord ID": null,
    "botto ID": null,
    "Control": null,
    "F.Track": null,
    "F.Pod": null,
    "Country": null,
    "Region": null,
    "Profile Note": null
  },
  {
    "Name": "mbatman72",
    "src ID": "joklrg78",
    "cs ID": null,
    "discord ID": null,
    "botto ID": null,
    "Control": null,
    "F.Track": null,
    "F.Pod": null,
    "Country": null,
    "Region": null,
    "Profile Note": null
  },
  {
    "Name": "Cainwood",
    "src ID": null,
    "cs ID": null,
    "discord ID": null,
    "botto ID": null,
    "Control": "Keyboard",
    "F.Track": "Executioner",
    "F.Pod": "Mars Guo",
    "Country": "US",
    "Region": null,
    "Profile Note": null
  },
  {
    "Name": "cocatriz",
    "src ID": null,
    "cs ID": null,
    "discord ID": null,
    "botto ID": null,
    "Control": null,
    "F.Track": null,
    "F.Pod": null,
    "Country": null,
    "Region": null,
    "Profile Note": null
  },
  {
    "Name": "CAVEBOTTING",
    "src ID": null,
    "cs ID": null,
    "discord ID": null,
    "botto ID": null,
    "Control": null,
    "F.Track": null,
    "F.Pod": null,
    "Country": null,
    "Region": null,
    "Profile Note": null
  },
  {
    "Name": "Radiant Variant",
    "src ID": null,
    "cs ID": null,
    "discord ID": "596517467740962845",
    "botto ID": null,
    "Control": null,
    "F.Track": null,
    "F.Pod": null,
    "Country": "US",
    "Region": null,
    "Profile Note": null
  },
  {
    "Name": "Marv",
    "src ID": null,
    "cs ID": null,
    "discord ID": "448026070587801601",
    "botto ID": null,
    "Control": null,
    "F.Track": null,
    "F.Pod": null,
    "Country": null,
    "Region": null,
    "Profile Note": null
  },
  {
    "Name": "Bip Carai",
    "src ID": null,
    "cs ID": null,
    "discord ID": "911784515821768745",
    "botto ID": null,
    "Control": null,
    "F.Track": null,
    "F.Pod": null,
    "Country": null,
    "Region": null,
    "Profile Note": null
  },
  {
    "Name": "Zed",
    "src ID": null,
    "cs ID": null,
    "discord ID": null,
    "botto ID": null,
    "Control": null,
    "F.Track": null,
    "F.Pod": null,
    "Country": "US",
    "Region": null,
    "Profile Note": null
  },
  {
    "Name": "WazaAenor",
    "src ID": null,
    "cs ID": null,
    "discord ID": null,
    "botto ID": null,
    "Control": null,
    "F.Track": null,
    "F.Pod": null,
    "Country": null,
    "Region": null,
    "Profile Note": null
  },
  {
    "Name": "Sakuru",
    "src ID": null,
    "cs ID": null,
    "discord ID": "1089684561602027690",
    "botto ID": null,
    "Control": null,
    "F.Track": null,
    "F.Pod": null,
    "Country": null,
    "Region": null,
    "Profile Note": null
  },
  {
    "Name": "theraginggamer095",
    "src ID": null,
    "cs ID": null,
    "discord ID": "499006288143974404",
    "botto ID": null,
    "Control": null,
    "F.Track": null,
    "F.Pod": null,
    "Country": null,
    "Region": null,
    "Profile Note": null
  },
  {
    "Name": "RamOfPluto",
    "src ID": null,
    "cs ID": null,
    "discord ID": "105066235766530048",
    "botto ID": null,
    "Control": null,
    "F.Track": null,
    "F.Pod": null,
    "Country": null,
    "Region": null,
    "Profile Note": null
  },
  {
    "Name": "Lilac Dryad",
    "src ID": null,
    "cs ID": null,
    "discord ID": "233448529186521089",
    "botto ID": "-NURcHSCVsb3e1fQYvj3s",
    "Control": null,
    "F.Track": null,
    "F.Pod": null,
    "Country": "US",
    "Region": null,
    "Profile Note": null
  },
  {
    "Name": "TDW 0333",
    "src ID": null,
    "cs ID": null,
    "discord ID": "461241711482372096",
    "botto ID": null,
    "Control": null,
    "F.Track": null,
    "F.Pod": null,
    "Country": null,
    "Region": null,
    "Profile Note": null
  },
  {},
  {},
  {},
  {},
  {},
  {},
  {},
  {},
  {},
  {},
  {},
  {},
  {},
  {},
  {},
  {},
  {},
  {},
  {},
  {},
  {},
  {},
  {},
  {},
  {},
  {},
  {},
  {},
  {},
  {},
  {},
  {},
  {},
  {},
  {},
  {},
  {},
  {},
  {},
  {},
  {},
  {},
  {},
  {},
  {},
  {},
  {},
  {},
  {},
  {},
  {},
  {},
  {},
  {},
  {},
  {},
  {},
  {},
  {},
  {},
  {},
  {},
  {},
  {},
  {},
  {},
  {},
  {},
  {},
  {},
  {},
  {},
  {},
  {},
  {},
  {},
  {},
  {},
  {},
  {},
  {},
  {},
  {},
  {},
  {},
  {},
  {},
  {},
  {},
  {},
  {},
  {},
  {},
  {},
  {},
  {},
  {},
  {},
  {},
  {},
  {},
  {},
  {},
  {},
  {},
  {},
  {},
  {},
  {},
  {},
  {},
  {},
  {},
  {},
  {},
  {},
  {},
  {},
  {},
  {},
  {},
  {},
  {},
  {},
  {},
  {},
  {},
  {},
  {},
  {},
  {},
  {},
  {},
  {},
  {},
  {},
  {},
  {},
  {},
  {},
  {},
  {},
  {},
  {},
  {},
  {},
  {},
  {},
  {},
  {},
  {},
  {},
  {},
  {},
  {},
  {},
  {},
  {},
  {},
  {},
  {},
  {},
  {},
  {},
  {},
  {},
  {},
  {},
  {},
  {},
  {},
  {},
  {},
  {},
  {},
  {},
  {},
  {},
  {},
  {},
  {},
  {},
  {},
  {},
  {},
  {},
  {},
  {},
  {},
  {},
  {},
  {},
  {},
  {},
  {},
  {},
  {},
  {},
  {},
  {},
  {},
  {},
  {},
  {},
  {},
  {},
  {},
  {},
  {},
  {},
  {},
  {},
  {},
  {},
  {},
  {},
  {},
  {},
  {},
  {},
  {},
  {},
  {},
  {},
  {},
  {},
  {},
  {},
  {},
  {},
  {},
  {},
  {},
  {},
  {},
  {},
  {},
  {},
  {},
  {},
  {},
  {},
  {},
  {},
  {},
  {},
  {},
  {},
  {},
  {},
  {},
  {},
  {},
  {},
  {},
  {},
  {},
  {},
  {},
  {},
  {},
  {},
  {},
  {},
  {},
  {},
  {},
  {},
  {},
  {},
  {},
  {},
  {},
  {},
  {},
  {},
  {},
  {},
  {},
  {},
  {},
  {},
  {},
  {},
  {},
  {},
  {},
  {},
  {},
  {},
  {},
  {},
  {},
  {},
  {},
  {},
  {},
  {},
  {},
  {},
  {},
  {},
  {},
  {},
  {},
  {},
  {},
  {},
  {},
  {},
  {},
  {},
  {},
  {},
  {},
  {},
  {},
  {},
  {},
  {},
  {},
  {},
  {},
  {},
  {},
  {},
  {},
  {},
  {},
  {},
  {},
  {},
  {},
  {},
  {},
  {},
  {},
  {},
  {},
  {},
  {},
  {},
  {},
  {},
  {},
  {},
  {},
  {},
  {},
  {},
  {},
  {},
  {},
  {},
  {},
  {},
  {},
  {},
  {},
  {},
  {},
  {},
  {},
  {},
  {},
  {},
  {},
  {},
  {},
  {},
  {},
  {},
  {},
  {},
  {},
  {},
  {},
  {},
  {},
  {},
  {},
  {},
  {},
  {},
  {},
  {},
  {},
  {},
  {},
  {},
  {},
  {},
  {},
  {},
  {},
  {},
  {},
  {},
  {},
  {},
  {},
  {},
  {},
  {},
  {},
  {},
  {},
  {},
  {},
  {},
  {},
  {},
  {},
  {},
  {},
  {},
  {},
  {},
  {},
  {},
  {},
  {},
  {},
  {},
  {},
  {},
  {},
  {},
  {},
  {},
  {},
  {},
  {},
  {},
  {},
  {},
  {},
  {},
  {},
  {},
  {},
  {},
  {},
  {},
  {},
  {},
  {},
  {},
  {},
  {},
  {},
  {},
  {},
  {},
  {},
  {},
  {},
  {},
  {},
  {},
  {},
  {},
  {},
  {},
  {},
  {},
  {},
  {},
  {},
  {},
  {},
  {},
  {},
  {},
  {},
  {},
  {},
  {},
  {},
  {},
  {},
  {},
  {},
  {},
  {},
  {},
  {},
  {},
  {},
  {},
  {},
  {},
  {},
  {},
  {},
  {},
  {},
  {},
  {},
  {},
  {},
  {},
  {},
  {},
  {},
  {},
  {},
  {},
  {},
  {},
  {},
  {},
  {},
  {},
  {},
  {},
  {},
  {},
  {},
  {},
  {},
  {},
  {},
  {},
  {},
  {},
  {},
  {},
  {},
  {},
  {},
  {},
  {},
  {},
  {},
  {},
  {},
  {},
  {},
  {},
  {},
  {},
  {},
  {},
  {},
  {},
  {},
  {},
  {},
  {},
  {},
  {},
  {},
  {},
  {},
  {},
  {},
  {},
  {},
  {},
  {},
  {},
  {},
  {},
  {},
  {},
  {},
  {},
  {},
  {},
  {},
  {},
  {},
  {},
  {},
  {},
  {},
  {},
  {},
  {},
  {},
  {},
  {},
  {},
  {},
  {},
  {},
  {},
  {},
  {},
  {},
  {},
  {},
  {},
  {},
  {},
  {},
  {},
  {},
  {},
  {},
  {},
  {},
  {},
  {},
  {},
  {},
  {},
  {},
  {},
  {},
  {},
  {},
  {},
  {},
  {},
  {},
  {},
  {},
  {},
  {},
  {},
  {},
  {},
  {},
  {},
  {},
  {},
  {},
  {},
  {},
  {},
  {},
  {},
  {},
  {},
  {},
  {},
  {},
  {
    "Name": "Mark109K",
    "src ID": "jngooz28",
    "cs ID": null,
    "discord ID": null,
    "botto ID": null,
    "Control": null,
    "F.Track": null,
    "F.Pod": null,
    "Country": null,
    "Region": null,
    "Profile Note": null
  },
  {
    "Name": "AshleyWave",
    "src ID": "8eep5778",
    "cs ID": null,
    "discord ID": null,
    "botto ID": null,
    "Control": null,
    "F.Track": null,
    "F.Pod": null,
    "Country": "US",
    "Region": null,
    "Profile Note": null
  },
  {
    "Name": "Gsterjkl1122",
    "src ID": "xykrv1n8",
    "cs ID": null,
    "discord ID": null,
    "botto ID": null,
    "Control": null,
    "F.Track": null,
    "F.Pod": null,
    "Country": null,
    "Region": null,
    "Profile Note": null
  },
  {
    "Name": "onionman790",
    "src ID": "8q555708",
    "cs ID": null,
    "discord ID": null,
    "botto ID": null,
    "Control": null,
    "F.Track": null,
    "F.Pod": null,
    "Country": null,
    "Region": null,
    "Profile Note": null
  },
  {
    "Name": "niwaka20",
    "src ID": "8rmdy2gj",
    "cs ID": null,
    "discord ID": null,
    "botto ID": null,
    "Control": null,
    "F.Track": null,
    "F.Pod": null,
    "Country": null,
    "Region": null,
    "Profile Note": null
  },
  {
    "Name": "Wuzzmi",
    "src ID": "x77rddyx",
    "cs ID": null,
    "discord ID": null,
    "botto ID": null,
    "Control": null,
    "F.Track": null,
    "F.Pod": null,
    "Country": null,
    "Region": null,
    "Profile Note": null
  },
  {
    "Name": "GeezHokk",
    "src ID": "jm6g7yo8",
    "cs ID": null,
    "discord ID": null,
    "botto ID": null,
    "Control": null,
    "F.Track": null,
    "F.Pod": null,
    "Country": null,
    "Region": null,
    "Profile Note": null
  },
  {
    "Name": "starwarsguy2018",
    "src ID": "jm61y7n8",
    "cs ID": null,
    "discord ID": null,
    "botto ID": null,
    "Control": null,
    "F.Track": null,
    "F.Pod": null,
    "Country": null,
    "Region": null,
    "Profile Note": null
  },
  {
    "Name": "Milhulse",
    "src ID": "8r62v368",
    "cs ID": null,
    "discord ID": null,
    "botto ID": null,
    "Control": null,
    "F.Track": null,
    "F.Pod": null,
    "Country": null,
    "Region": null,
    "Profile Note": null
  },
  {
    "Name": "QuietSandshrew",
    "src ID": "xkzmrg6x",
    "cs ID": null,
    "discord ID": null,
    "botto ID": null,
    "Control": null,
    "F.Track": null,
    "F.Pod": null,
    "Country": null,
    "Region": null,
    "Profile Note": null
  },
  {
    "Name": "Hellshrekness",
    "src ID": "j20eekox",
    "cs ID": null,
    "discord ID": null,
    "botto ID": null,
    "Control": null,
    "F.Track": null,
    "F.Pod": null,
    "Country": null,
    "Region": null,
    "Profile Note": null
  },
  {
    "Name": "Lambchop123",
    "src ID": "8gzm737j",
    "cs ID": null,
    "discord ID": null,
    "botto ID": null,
    "Control": null,
    "F.Track": null,
    "F.Pod": null,
    "Country": null,
    "Region": null,
    "Profile Note": null
  },
  {
    "Name": "TDW_0333",
    "src ID": "xyoe4owj",
    "cs ID": null,
    "discord ID": null,
    "botto ID": null,
    "Control": null,
    "F.Track": null,
    "F.Pod": null,
    "Country": null,
    "Region": null,
    "Profile Note": null
  },
  {
    "Name": "Camsponge",
    "src ID": "8lzrq0lx",
    "cs ID": null,
    "discord ID": null,
    "botto ID": null,
    "Control": null,
    "F.Track": null,
    "F.Pod": null,
    "Country": null,
    "Region": null,
    "Profile Note": null
  },
  {
    "Name": "TirTheTerror",
    "src ID": "8lz6n4lx",
    "cs ID": null,
    "discord ID": null,
    "botto ID": null,
    "Control": null,
    "F.Track": null,
    "F.Pod": null,
    "Country": null,
    "Region": null,
    "Profile Note": null
  },
  {
    "Name": "PD4FR",
    "src ID": "8gmwg118",
    "cs ID": null,
    "discord ID": null,
    "botto ID": null,
    "Control": null,
    "F.Track": null,
    "F.Pod": null,
    "Country": null,
    "Region": null,
    "Profile Note": null
  }
]